Workbook
Name APPLE_MUSIC_EXPENSES: 'NOVEMBER APPLE MUSIC EXPENSES'!$I$4

Sheet DASHBOARD
B3: APPLE MUSIC
B4: MONTH | C4: SALES | D4: EXPENSES | E4: GROSS PROFIT
B5: JANUARY | C5: =SUM('Total Customer Apple Music'!B204) -> 125
B6: FEBRUARY | C6: =SUM('Total Customer Apple Music'!B199:B203) -> 620
B7: MARCH | C7: =SUM('Total Customer Apple Music'!B191:B198) -> 1290
B8: APRIL | C8: =SUM('Total Customer Apple Music'!B172:B190) -> 1715
B9: MAY | C9: =SUM('Total Customer Apple Music'!B167:B171) -> 565
B10: JUNE | C10: =SUM('Total Customer Apple Music'!B163:B166) -> 435
B11: JULY | C11: =SUM('Total Customer Apple Music'!B144:B162) -> 3385
B12: AUGUST | C12: =SUM('Total Customer Apple Music'!B120:B143) -> 4520
B13: SEPTEMBER | C13: =SUM('Total Customer Apple Music'!B100:B119) -> 4485
B14: OCTOBER | C14: =SUM('Total Customer Apple Music'!B56:B99) -> 6150
B15: NOVEMBER | C15: =SUM('Total Customer Apple Music'!B6:B55) -> 3687 | D15: =APPLE_MUSIC_EXPENSES -> 1005 | E15: =C15-D15 -> 2682
B16: DECEMBER | C16: =SUM('Total Customer Apple Music'!B2:B5) -> 161
B17: TOTALS | C17: =SUM(C5:C16) -> 27138 | D17: =SUM(D5:D16) -> 1005 | E17: =SUM(E5:E16) -> 2682
B20: AMAZON PRIME
B21: MONTH | C21: SALES | D21: EXPENSES | E21: GROSS PROFIT
B22: NOVEMBER | C22: =SUM('PRIME VIDEO'!B2:B12) -> 1705 | D22: =4*161 -> 644 | E22: =C22-D22 -> 1061
B23: DECEMBER | C23: ='PRIME VIDEO'!B13 -> 65 | D23: 161 | E23: =C23-D23 -> -96
B25: SPOTIFY
B26: MONTH | C26: SALES | D26: EXPENSES | E26: GROSS PROFIT
B27: NOVEMBER | C27: 715 | D27: =156*2 -> 312 | E27: =C27-D27 -> 403
B28: DECEMBER | C28: =SUM('Total Customer Apple Music'!B221:B225) -> 0
B31: DSTV
B32: MONTH | C32: SALES | D32: EXPENSES | E32: GROSS PROFIT
B33: NOVEMBER | C33: =SUM('DSTV CUSTOMERS'!B4:B6) -> 485 | D33: =40*3 -> 120 | E33: =C33-D33 -> 365
B34: DECEMBER | C34: =SUM('Total Customer Apple Music'!B227:B231) -> 0
B36: ICLOUD STORAGE
B37: MONTH | C37: SALES | D37: EXPENSES | E37: GROSS PROFIT
B38: NOVEMBER | C38: =SUM('ICLOUD STORAGE '!B12:B13) -> 140 | D38: 80 | E38: =C38-D38 -> 60
B39: DECEMBER | C39: =SUM('Total Customer Apple Music'!B232:B236) -> 0 | E39: =C39-D39 -> 0

Sheet COSTS
B4: APPLE MUSIC PREMIUM | D4: Accounts | E4: COST/AC | I4: BLACK FRIDAY | K4: Accounts | L4: COST/AC
B6: MONTHS | C6: FEES | I6: MOBTHS | J6: PRICE
B7: 1 | C7: 65 | D7: 1 | E7: - | I7: 1 | J7: 32 | K7: 1 | L7: -
B8: 2 | C8: 125 | D8: 1 | E8: - | I8: 2 | J8: 65 | K8: 1 | L8: -
B9: 3 | C9: 185 | D9: 1 | E9: - | I9: 3 | J9: 100 | K9: 1 | L9: -
B10: 4 | C10: 245 | D10: 1 | E10: - | I10: 4 | J10: 135 | K10: 1 | L10: -
B11: 5 | C11: 275 | D11: 1 | E11: 3 | G11: =E11*24 -> 72 | I11: 5 | J11: 275 | K11: 1 | L11: 3 | M11: =L11*24 -> 72
B12: 6 | C12: 325 | D12: 1 | E12: 6 | G12: =E12*24 -> 144 | I12: 6 | J12: 195 | K12: 1 | L12: 6 | M12: =L12*24 -> 144
B13: 12 | C13: 450 | D13: 2 | E13: 6 | G13: =E13*24 -> 144 | I13: 12 | J13: 225 | K13: 2 | L13: 6 | M13: =L13*24 -> 144
B18: PRIME VIDEO | D18: Accounts | E18: COST/AC | I18: BLACK FRIDAY | K18: Accounts
B20: 1 month | C20: 65 | D20: 1 | E20: 161 | I20: 1 months | J20: 50 | K20: 1
B21: 2 months | C21: 105 | D21: 1 | E21: 161 | I21: 2 months | J21: 98 | K21: 1
B22: 3 months | C22: 155 | D22: 1 | E22: 161 | I22: 3 months | J22: 150 | K22: 1
I23: 6 months | J23: 225 | K23: 1
I24: 1 year | J24: 475 | K24: 2
B27: SHOWMAX | D27: Accounts | E27: COST/AC
B29: 1 month | C29: 55 | D29: 1
B30: 2 months | C30: 100 | D30: 1
B31: 3 months | C31: 145 | D31: 1
B35: CRUNCHYROLL | D35: Accounts | E35: COST/AC
B37: 1 month | C37: 45 | D37: 1 | E37: 70
B38: 2 months | C38: 95 | D38: 1 | E38: 70
B39: 3 months | C39: 145 | D39: 1 | E39: 70
B42: NETFLIX | D42: Accounts | E42: COST/AC
B44: 1 month | C44: 100 | D44: 1 | E44: 260
B45: 2 months | C45: 180 | D45: 1 | E45: 260 | F45: FAMILY OF 5
B46: 3 months | C46: 250 | D46: 1 | E46: 260
B49: APPLE ICLOUD | D49: Accounts | E49: COST/AC
B51: 1 month | C51: 70 | D51: 1 | E51: 40
B52: 2 months | C52: 200 | D52: 1 | E52: 40
B53: 3 months | C53: 350 | D53: 1 | E53: 40
B56: SPOTIFY | D56: Accounts | E56: COST/AC
B58: 1 month | C58: 70 | D58: 1 | E58: 156 | F58: FAMILY OF 5
B59: 2 months | C59: 200 | D59: 1 | E59: 156
B60: 3 months | C60: 350 | D60: 1 | E60: 156 | F60: =6*E59 -> 936

Sheet Total Customer Apple Music
A1: Months | B1: price | C1: Family | D1: Paid date | E1: Expire date | F1: Number | G1: Name | H1: TODAYS DATE | I1: DUE DATE | J1: STATUS | K1: MONTH
A2: 1 | B2: =VLOOKUP(A2, COSTS!$I$7:$J$13, 2, FALSE) -> 32 | C2: Isaac | D2: 45997 | E2: 46028 | F2: 777768771 | G2: Isaac Nseluka | H2: =NOW() -> 46020.438 | I2: =E2-H2 -> 7.5620179 | J2: =IF(I2<=0, "EXPIRED", IF(I2<=7, "DUE THIS WEEK", IF(I2<=30, "DUE THIS MONTH", "ACTIVE"))) -> DUE THIS MONTH | K2: DECEMBER
A3: 2 | B3: =VLOOKUP(A3, COSTS!$I$7:$J$13, 2, FALSE) -> 65 | C3: Sekelani | D3: 45997 | E3: 45997 | F3: 096 7365292 | G3: Zoey | H3: =NOW() -> 46020.438 | I3: =E3-H3 -> -23.437982 | J3: =IF(I3<=0, "EXPIRED", IF(I3<=7, "DUE THIS WEEK", IF(I3<=30, "DUE THIS MONTH", "ACTIVE"))) -> EXPIRED | K3: DECEMBER
A4: 1 | B4: =VLOOKUP(A4, COSTS!$I$7:$J$13, 2, FALSE) -> 32 | C4: Paul | D4: 45995 | E4: 46026 | F4: 773368022 | G4: Levy | H4: =NOW() -> 46020.438 | I4: =E4-H4 -> 5.5620179 | J4: =IF(I4<=0, "EXPIRED", IF(I4<=7, "DUE THIS WEEK", IF(I4<=30, "DUE THIS MONTH", "ACTIVE"))) -> DUE THIS WEEK | K4: DECEMBER
A5: 1 | B5: =VLOOKUP(A5, COSTS!$I$7:$J$13, 2, FALSE) -> 32 | C5: Gabriella | D5: 45993 | E5: 46024 | F5: 975201345 | G5: Chifuniro Zulu | H5: =NOW() -> 46020.438 | I5: =E5-H5 -> 3.5620179 | J5: =IF(I5<=0, "EXPIRED", IF(I5<=7, "DUE THIS WEEK", IF(I5<=30, "DUE THIS MONTH", "ACTIVE"))) -> DUE THIS WEEK | K5: DECEMBER
A6: 1 | B6: =VLOOKUP(A6, COSTS!$I$7:$J$13, 2, FALSE) -> 32 | C6: Stephen | D6: 45990 | E6: 46020 | F6: 964668081 | G6: Gianna mabuku | H6: =NOW() -> 46020.438 | I6: =E6-H6 -> -0.43798206 | J6: =IF(I6<=0, "EXPIRED", IF(I6<=7, "DUE THIS WEEK", IF(I6<=30, "DUE THIS MONTH", "ACTIVE"))) -> EXPIRED | K6: NOVEMBER
A7: 1 | B7: =VLOOKUP(A7, COSTS!$I$7:$J$13, 2, FALSE) -> 32 | C7: Kabaya | D7: 45990 | E7: 46020 | F7: 957985331 | G7: Elizabeth Daka | H7: =NOW() -> 46020.438 | I7: =E7-H7 -> -0.43798206 | J7: =IF(I7<=0, "EXPIRED", IF(I7<=7, "DUE THIS WEEK", IF(I7<=30, "DUE THIS MONTH", "ACTIVE"))) -> EXPIRED | K7: NOVEMBER
A8: 1 | B8: =VLOOKUP(A8, COSTS!$I$7:$J$13, 2, FALSE) -> 32 | C8: Stephen | D8: 45990 | E8: 46020 | F8: 978490644 | G8: Tapiwa Banda | H8: =NOW() -> 46020.438 | I8: =E8-H8 -> -0.43798206 | J8: =IF(I8<=0, "EXPIRED", IF(I8<=7, "DUE THIS WEEK", IF(I8<=30, "DUE THIS MONTH", "ACTIVE"))) -> EXPIRED | K8: NOVEMBER
A9: 1 | B9: =VLOOKUP(A9, COSTS!$I$7:$J$13, 2, FALSE) -> 32 | C9: Caleb | D9: 45990 | E9: 46020 | F9: 096 0992424 | G9: Zango m | H9: =NOW() -> 46020.438 | I9: =E9-H9 -> -0.43798206 | J9: =IF(I9<=0, "EXPIRED", IF(I9<=7, "DUE THIS WEEK", IF(I9<=30, "DUE THIS MONTH", "ACTIVE"))) -> EXPIRED | K9: NOVEMBER
A10: 1 | B10: =VLOOKUP(A10, COSTS!$I$7:$J$13, 2, FALSE) -> 32 | C10: Caleb | D10: 45989 | E10: 46019 | F10: 767070164 | G10: Benjamin lukamba | H10: =NOW() -> 46020.438 | I10: =E10-H10 -> -1.4379821 | J10: =IF(I10<=0, "EXPIRED", IF(I10<=7, "DUE THIS WEEK", IF(I10<=30, "DUE THIS MONTH", "ACTIVE"))) -> EXPIRED | K10: NOVEMBER
A11: 3 | B11: =VLOOKUP(A11, COSTS!$I$7:$J$13, 2, FALSE) -> 100 | D11: 45989 | E11: 45716 | F11: 978478417 | G11: Paul Katongo | H11: =NOW() -> 46020.438 | I11: =E11-H11 -> -304.43798 | J11: =IF(I11<=0, "EXPIRED", IF(I11<=7, "DUE THIS WEEK", IF(I11<=30, "DUE THIS MONTH", "ACTIVE"))) -> EXPIRED | K11: NOVEMBER
A12: 3 | B12: =VLOOKUP(A12, COSTS!$I$7:$J$13, 2, FALSE) -> 100 | C12: Kabaya | D12: 45989 | E12: 46081 | F12: 60 97 5467109 | G12: Ameenah Fatacky | H12: =NOW() -> 46020.438 | I12: =E12-H12 -> 60.562018 | J12: =IF(I12<=0, "EXPIRED", IF(I12<=7, "DUE THIS WEEK", IF(I12<=30, "DUE THIS MONTH", "ACTIVE"))) -> ACTIVE | K12: NOVEMBER
A13: 2 | B13: =VLOOKUP(A13, COSTS!$I$7:$J$13, 2, FALSE) -> 65 | C13: Mukoma | D13: 45989 | E13: 46050 | F13: 097 2159192 | G13: Nelson Malunga | H13: =NOW() -> 46020.438 | I13: =E13-H13 -> 29.562018 | J13: =IF(I13<=0, "EXPIRED", IF(I13<=7, "DUE THIS WEEK", IF(I13<=30, "DUE THIS MONTH", "ACTIVE"))) -> DUE THIS MONTH | K13: NOVEMBER
A14: 2 | B14: =VLOOKUP(A14, COSTS!$I$7:$J$13, 2, FALSE) -> 65 | D14: 45989 | E14: 46050 | F14: 961817836 | G14: Chiza Ngoma-Nicholas Jr. | H14: =NOW() -> 46020.438 | I14: =E14-H14 -> 29.562018 | J14: =IF(I14<=0, "EXPIRED", IF(I14<=7, "DUE THIS WEEK", IF(I14<=30, "DUE THIS MONTH", "ACTIVE"))) -> DUE THIS MONTH | K14: NOVEMBER
A15: 12 | B15: =VLOOKUP(A15, COSTS!$I$7:$J$13, 2, FALSE) -> 225 | C15: Wesly | D15: 45988 | E15: 46353 | F15: 973208399 | G15: temwani nawale | H15: =NOW() -> 46020.438 | I15: =E15-H15 -> 332.56202 | J15: =IF(I15<=0, "EXPIRED", IF(I15<=7, "DUE THIS WEEK", IF(I15<=30, "DUE THIS MONTH", "ACTIVE"))) -> ACTIVE | K15: NOVEMBER
A16: 2 | B16: =VLOOKUP(A16, COSTS!$I$7:$J$13, 2, FALSE) -> 65 | C16: Ziko | D16: 45988 | E16: 46049 | F16: 097 1997704 | G16: Salim | H16: =NOW() -> 46020.438 | I16: =E16-H16 -> 28.562018 | J16: =IF(I16<=0, "EXPIRED", IF(I16<=7, "DUE THIS WEEK", IF(I16<=30, "DUE THIS MONTH", "ACTIVE"))) -> DUE THIS MONTH | K16: NOVEMBER
A17: 1 | B17: =VLOOKUP(A17, COSTS!$I$7:$J$13, 2, FALSE) -> 32 | C17: Hussan | D17: 45988 | E17: 46018 | F17: 260776149435 | G17: Mukuka Bwalya | H17: =NOW() -> 46020.438 | I17: =E17-H17 -> -2.4379821 | J17: =IF(I17<=0, "EXPIRED", IF(I17<=7, "DUE THIS WEEK", IF(I17<=30, "DUE THIS MONTH", "ACTIVE"))) -> EXPIRED | K17: NOVEMBER
A18: 1 | B18: =VLOOKUP(A18, COSTS!$I$7:$J$13, 2, FALSE) -> 32 | C18: Wumi | D18: 45987 | E18: 46017 | F18: 960161606 | G18: Erykah Daff | H18: =NOW() -> 46020.438 | I18: =E18-H18 -> -3.4379821 | J18: =IF(I18<=0, "EXPIRED", IF(I18<=7, "DUE THIS WEEK", IF(I18<=30, "DUE THIS MONTH", "ACTIVE"))) -> EXPIRED | K18: NOVEMBER
A19: 1 | B19: =VLOOKUP(A19, COSTS!$I$7:$J$13, 2, FALSE) -> 32 | C19: Tinashe | D19: 45987 | E19: 46017 | F19: =260770773549 -> 260770773549 | G19: Wana Moonga | H19: =NOW() -> 46020.438 | I19: =E19-H19 -> -3.4379821 | J19: =IF(I19<=0, "EXPIRED", IF(I19<=7, "DUE THIS WEEK", IF(I19<=30, "DUE THIS MONTH", "ACTIVE"))) -> EXPIRED | K19: NOVEMBER
A20: 2 | B20: =VLOOKUP(A20, COSTS!$I$7:$J$13, 2, FALSE) -> 65 | C20: Wumi | D20: 45986 | E20: 46047 | F20: 972371009 | G20: Twiase | H20: =NOW() -> 46020.438 | I20: =E20-H20 -> 26.562018 | J20: =IF(I20<=0, "EXPIRED", IF(I20<=7, "DUE THIS WEEK", IF(I20<=30, "DUE THIS MONTH", "ACTIVE"))) -> DUE THIS MONTH | K20: NOVEMBER
A21: 2 | B21: =VLOOKUP(A21, COSTS!$I$7:$J$13, 2, FALSE) -> 65 | C21: Wumi | D21: 45986 | E21: 46047 | F21: 771993800 | G21: Tanaka | H21: =NOW() -> 46020.438 | I21: =E21-H21 -> 26.562018 | J21: =IF(I21<=0, "EXPIRED", IF(I21<=7, "DUE THIS WEEK", IF(I21<=30, "DUE THIS MONTH", "ACTIVE"))) -> DUE THIS MONTH | K21: NOVEMBER
A22: 2 | B22: =VLOOKUP(A22, COSTS!$I$7:$J$13, 2, FALSE) -> 65 | C22: Zile | D22: 45985 | E22: 46077 | F22: 975741666 | G22: Flo | H22: =NOW() -> 46020.438 | I22: =E22-H22 -> 56.562018 | J22: =IF(I22<=0, "EXPIRED", IF(I22<=7, "DUE THIS WEEK", IF(I22<=30, "DUE THIS MONTH", "ACTIVE"))) -> ACTIVE | K22: NOVEMBER
A23: 2 | B23: =VLOOKUP(A23, COSTS!$I$7:$J$13, 2, FALSE) -> 65 | C23: Zile | D23: 45985 | E23: 46046 | F23: 097 9758092 | G23: Ethan mvula | H23: =NOW() -> 46020.438 | I23: =E23-H23 -> 25.562018 | J23: =IF(I23<=0, "EXPIRED", IF(I23<=7, "DUE THIS WEEK", IF(I23<=30, "DUE THIS MONTH", "ACTIVE"))) -> DUE THIS MONTH | K23: NOVEMBER
A24: 2 | B24: =VLOOKUP(A24, COSTS!$I$7:$J$13, 2, FALSE) -> 65 | D24: 45985 | E24: 46046 | F24: 973724846 | G24: Milo Sililo | H24: =NOW() -> 46020.438 | I24: =E24-H24 -> 25.562018 | J24: =IF(I24<=0, "EXPIRED", IF(I24<=7, "DUE THIS WEEK", IF(I24<=30, "DUE THIS MONTH", "ACTIVE"))) -> DUE THIS MONTH | K24: NOVEMBER
A25: 3 | B25: =VLOOKUP(A25, COSTS!$I$7:$J$13, 2, FALSE) -> 100 | C25: Mwenya | D25: 45984 | E25: 46076 | F25: 776552506 | G25: Latifah | H25: =NOW() -> 46020.438 | I25: =E25-H25 -> 55.562018 | J25: =IF(I25<=0, "EXPIRED", IF(I25<=7, "DUE THIS WEEK", IF(I25<=30, "DUE THIS MONTH", "ACTIVE"))) -> ACTIVE | K25: NOVEMBER
A26: 2 | B26: =VLOOKUP(A26, COSTS!$I$7:$J$13, 2, FALSE) -> 65 | C26: Namooya | D26: 45984 | E26: 46045 | F26: 954049056 | G26: Jojo | H26: =NOW() -> 46020.438 | I26: =E26-H26 -> 24.562018 | J26: =IF(I26<=0, "EXPIRED", IF(I26<=7, "DUE THIS WEEK", IF(I26<=30, "DUE THIS MONTH", "ACTIVE"))) -> DUE THIS MONTH | K26: NOVEMBER
A27: 1 | B27: =VLOOKUP(A27, COSTS!$I$7:$J$13, 2, FALSE) -> 32 | C27: Kanyanta | D27: 45984 | E27: 46014 | F27: 097 1833083 | G27: Rafael | H27: =NOW() -> 46020.438 | I27: =E27-H27 -> -6.4379821 | J27: =IF(I27<=0, "EXPIRED", IF(I27<=7, "DUE THIS WEEK", IF(I27<=30, "DUE THIS MONTH", "ACTIVE"))) -> EXPIRED | K27: NOVEMBER
A28: 3 | B28: =VLOOKUP(A28, COSTS!$I$7:$J$13, 2, FALSE) -> 100 | C28: Warren | D28: 45982 | E28: 46102 | F28: 772734094 | G28: Jackie | H28: =NOW() -> 46020.438 | I28: =E28-H28 -> 81.562018 | J28: =IF(I28<=0, "EXPIRED", IF(I28<=7, "DUE THIS WEEK", IF(I28<=30, "DUE THIS MONTH", "ACTIVE"))) -> ACTIVE | K28: NOVEMBER
A29: 2 | B29: =VLOOKUP(A29, COSTS!$I$7:$J$13, 2, FALSE) -> 65 | C29: Ziko | D29: 45982 | E29: 46043 | F29: 967990940 | G29: Joy | H29: =NOW() -> 46020.438 | I29: =E29-H29 -> 22.562018 | J29: =IF(I29<=0, "EXPIRED", IF(I29<=7, "DUE THIS WEEK", IF(I29<=30, "DUE THIS MONTH", "ACTIVE"))) -> DUE THIS MONTH | K29: NOVEMBER
A30: 1 | B30: =VLOOKUP(A30, COSTS!$I$7:$J$13, 2, FALSE) -> 32 | C30: Warren | D30: 45982 | E30: 46012 | F30: 097 1016943 | G30: Jo-Ann | H30: =NOW() -> 46020.438 | I30: =E30-H30 -> -8.4379821 | J30: =IF(I30<=0, "EXPIRED", IF(I30<=7, "DUE THIS WEEK", IF(I30<=30, "DUE THIS MONTH", "ACTIVE"))) -> EXPIRED | K30: NOVEMBER
A31: 3 | B31: =VLOOKUP(A31, COSTS!$I$7:$J$13, 2, FALSE) -> 100 | C31: Ziko | D31: 45981 | E31: 46073 | F31: 770438283 | G31: Nissa | H31: =NOW() -> 46020.438 | I31: =E31-H31 -> 52.562018 | J31: =IF(I31<=0, "EXPIRED", IF(I31<=7, "DUE THIS WEEK", IF(I31<=30, "DUE THIS MONTH", "ACTIVE"))) -> ACTIVE | K31: NOVEMBER
A32: 2 | B32: =VLOOKUP(A32, COSTS!$I$7:$J$13, 2, FALSE) -> 65 | C32: Mwitwa | D32: 45978 | E32: 46070 | F32: 0 96 8748589 | G32: Vanessa 2 | H32: =NOW() -> 46020.438 | I32: =E32-H32 -> 49.562018 | J32: =IF(I32<=0, "EXPIRED", IF(I32<=7, "DUE THIS WEEK", IF(I32<=30, "DUE THIS MONTH", "ACTIVE"))) -> ACTIVE | K32: NOVEMBER
A33: 2 | B33: =VLOOKUP(A33, COSTS!$I$7:$J$13, 2, FALSE) -> 65 | C33: Chipo | D33: 45978 | E33: 46039 | F33: 095 7999876 | G33: Mutibo | H33: =NOW() -> 46020.438 | I33: =E33-H33 -> 18.562018 | J33: =IF(I33<=0, "EXPIRED", IF(I33<=7, "DUE THIS WEEK", IF(I33<=30, "DUE THIS MONTH", "ACTIVE"))) -> DUE THIS MONTH | K33: NOVEMBER
A34: 1 | B34: =VLOOKUP(A34, COSTS!$I$7:$J$13, 2, FALSE) -> 32 | C34: Agness | D34: 45978 | E34: 46008 | F34: 761673610 | G34: Niza sampa | H34: =NOW() -> 46020.438 | I34: =E34-H34 -> -12.437982 | J34: =IF(I34<=0, "EXPIRED", IF(I34<=7, "DUE THIS WEEK", IF(I34<=30, "DUE THIS MONTH", "ACTIVE"))) -> EXPIRED | K34: NOVEMBER
A35: 1 | B35: =VLOOKUP(A35, COSTS!$I$7:$J$13, 2, FALSE) -> 32 | C35: Stephan | D35: 45978 | E35: 46008 | F35: 976433541 | G35: Alick Luchembe | H35: =NOW() -> 46020.438 | I35: =E35-H35 -> -12.437982 | J35: =IF(I35<=0, "EXPIRED", IF(I35<=7, "DUE THIS WEEK", IF(I35<=30, "DUE THIS MONTH", "ACTIVE"))) -> EXPIRED | K35: NOVEMBER
A36: 1 | B36: =VLOOKUP(A36, COSTS!$I$7:$J$13, 2, FALSE) -> 32 | C36: Chipo | D36: 45978 | E36: 46008 | F36: 097 0126202 | G36: Georgina Banda | H36: =NOW() -> 46020.438 | I36: =E36-H36 -> -12.437982 | J36: =IF(I36<=0, "EXPIRED", IF(I36<=7, "DUE THIS WEEK", IF(I36<=30, "DUE THIS MONTH", "ACTIVE"))) -> EXPIRED | K36: NOVEMBER
A37: 2 | B37: =VLOOKUP(A37, COSTS!$I$7:$J$13, 2, FALSE) -> 65 | C37: Chichi | D37: 45977 | E37: 46038 | F37: 278 874 4694 | G37: Zima | H37: =NOW() -> 46020.438 | I37: =E37-H37 -> 17.562018 | J37: =IF(I37<=0, "EXPIRED", IF(I37<=7, "DUE THIS WEEK", IF(I37<=30, "DUE THIS MONTH", "ACTIVE"))) -> DUE THIS MONTH | K37: NOVEMBER
A38: 3 | B38: =VLOOKUP(A38, COSTS!$I$7:$J$13, 2, FALSE) -> 100 | C38: Ziko | D38: 45976 | E38: 46068 | F38: 0 97 3809971 | G38: Chikondi | H38: =NOW() -> 46020.438 | I38: =E38-H38 -> 47.562018 | J38: =IF(I38<=0, "EXPIRED", IF(I38<=7, "DUE THIS WEEK", IF(I38<=30, "DUE THIS MONTH", "ACTIVE"))) -> ACTIVE | K38: NOVEMBER
A39: 2 | B39: =VLOOKUP(A39, COSTS!$I$7:$J$13, 2, FALSE) -> 65 | C39: Hassan | D39: 45976 | E39: 46037 | F39: 773740049 | G39: Tiwonge | H39: =NOW() -> 46020.438 | I39: =E39-H39 -> 16.562018 | J39: =IF(I39<=0, "EXPIRED", IF(I39<=7, "DUE THIS WEEK", IF(I39<=30, "DUE THIS MONTH", "ACTIVE"))) -> DUE THIS MONTH | K39: NOVEMBER
A40: 2 | B40: =VLOOKUP(A40, COSTS!$I$7:$J$13, 2, FALSE) -> 65 | C40: Chipo | D40: 45976 | E40: 46037 | F40: 097 0633260 | G40: Kassie 2 | H40: =NOW() -> 46020.438 | I40: =E40-H40 -> 16.562018 | J40: =IF(I40<=0, "EXPIRED", IF(I40<=7, "DUE THIS WEEK", IF(I40<=30, "DUE THIS MONTH", "ACTIVE"))) -> DUE THIS MONTH | K40: NOVEMBER
A41: 1 | B41: =VLOOKUP(A41, COSTS!$I$7:$J$13, 2, FALSE) -> 32 | C41: Princess | D41: 45976 | E41: 46006 | F41: 772691176 | G41: Michelle | H41: =NOW() -> 46020.438 | I41: =E41-H41 -> -14.437982 | J41: =IF(I41<=0, "EXPIRED", IF(I41<=7, "DUE THIS WEEK", IF(I41<=30, "DUE THIS MONTH", "ACTIVE"))) -> EXPIRED | K41: NOVEMBER
A42: 1 | B42: =VLOOKUP(A42, COSTS!$I$7:$J$13, 2, FALSE) -> 32 | C42: Chichi | D42: 45976 | E42: 46006 | F42: 263 78 874 4694 | G42: Yamihle | H42: =NOW() -> 46020.438 | I42: =E42-H42 -> -14.437982 | J42: =IF(I42<=0, "EXPIRED", IF(I42<=7, "DUE THIS WEEK", IF(I42<=30, "DUE THIS MONTH", "ACTIVE"))) -> EXPIRED | K42: NOVEMBER
A43: 6 | B43: =VLOOKUP(A43, COSTS!$I$7:$J$13, 2, FALSE) -> 195 | C43: Mwenya | D43: 45975 | E43: 46067 | F43: 60779320678 | G43: David sampa | H43: =NOW() -> 46020.438 | I43: =E43-H43 -> 46.562018 | J43: =IF(I43<=0, "EXPIRED", IF(I43<=7, "DUE THIS WEEK", IF(I43<=30, "DUE THIS MONTH", "ACTIVE"))) -> ACTIVE | K43: NOVEMBER
A44: 2 | B44: =VLOOKUP(A44, COSTS!$I$7:$J$13, 2, FALSE) -> 65 | C44: Tionge | D44: 45975 | E44: 46036 | F44: 097 0702121 | G44: Thwani | H44: =NOW() -> 46020.438 | I44: =E44-H44 -> 15.562018 | J44: =IF(I44<=0, "EXPIRED", IF(I44<=7, "DUE THIS WEEK", IF(I44<=30, "DUE THIS MONTH", "ACTIVE"))) -> DUE THIS MONTH | K44: NOVEMBER
A45: 1 | B45: =VLOOKUP(A45, COSTS!$I$7:$J$13, 2, FALSE) -> 32 | D45: 45975 | E45: 46005 | F45: 097 5367166 | G45: Tehillah | H45: =NOW() -> 46020.438 | I45: =E45-H45 -> -15.437982 | J45: =IF(I45<=0, "EXPIRED", IF(I45<=7, "DUE THIS WEEK", IF(I45<=30, "DUE THIS MONTH", "ACTIVE"))) -> EXPIRED | K45: NOVEMBER
A46: 3 | B46: =VLOOKUP(A46, COSTS!$I$7:$J$13, 2, FALSE) -> 100 | C46: Panji | D46: 45974 | E46: 46035 | F46: 774967746 | G46: MB | H46: =NOW() -> 46020.438 | I46: =E46-H46 -> 14.562018 | J46: =IF(I46<=0, "EXPIRED", IF(I46<=7, "DUE THIS WEEK", IF(I46<=30, "DUE THIS MONTH", "ACTIVE"))) -> DUE THIS MONTH | K46: NOVEMBER
A47: 12 | B47: =VLOOKUP(A47, COSTS!$I$7:$J$13, 2, FALSE) -> 225 | C47: Panji | D47: 45973 | E47: 46368 | F47: 768846867 | G47: Mwenya 3 | H47: =NOW() -> 46020.438 | I47: =E47-H47 -> 347.56202 | J47: =IF(I47<=0, "EXPIRED", IF(I47<=7, "DUE THIS WEEK", IF(I47<=30, "DUE THIS MONTH", "ACTIVE"))) -> ACTIVE | K47: NOVEMBER
A48: 3 | B48: =VLOOKUP(A48, COSTS!$I$7:$J$13, 2, FALSE) -> 100 | C48: Panji | D48: 45973 | E48: 46065 | F48: 096 7101367 | G48: Chikondi | H48: =NOW() -> 46020.438 | I48: =E48-H48 -> 44.562018 | J48: =IF(I48<=0, "EXPIRED", IF(I48<=7, "DUE THIS WEEK", IF(I48<=30, "DUE THIS MONTH", "ACTIVE"))) -> ACTIVE | K48: NOVEMBER
A49: 3 | B49: =VLOOKUP(A49, COSTS!$I$7:$J$13, 2, FALSE) -> 100 | C49: Panji | D49: 45973 | E49: 46065 | F49: 776624932 | G49: Clarence | H49: =NOW() -> 46020.438 | I49: =E49-H49 -> 44.562018 | J49: =IF(I49<=0, "EXPIRED", IF(I49<=7, "DUE THIS WEEK", IF(I49<=30, "DUE THIS MONTH", "ACTIVE"))) -> ACTIVE | K49: NOVEMBER
A50: 2 | B50: =VLOOKUP(A50, COSTS!$I$7:$J$13, 2, FALSE) -> 65 | C50: 𝐇𝐚𝐤𝐞𝐞𝐦 | D50: 45972 | E50: 46033 | F50: 966944143 | G50: Zoe | H50: =NOW() -> 46020.438 | I50: =E50-H50 -> 12.562018 | J50: =IF(I50<=0, "EXPIRED", IF(I50<=7, "DUE THIS WEEK", IF(I50<=30, "DUE THIS MONTH", "ACTIVE"))) -> DUE THIS MONTH | K50: NOVEMBER
A51: 2 | B51: =VLOOKUP(A51, COSTS!$I$7:$J$13, 2, FALSE) -> 65 | C51: Wendy | D51: 45972 | E51: 46033 | F51: 773953416 | G51: Tyann | H51: =NOW() -> 46020.438 | I51: =E51-H51 -> 12.562018 | J51: =IF(I51<=0, "EXPIRED", IF(I51<=7, "DUE THIS WEEK", IF(I51<=30, "DUE THIS MONTH", "ACTIVE"))) -> DUE THIS MONTH | K51: NOVEMBER
A52: 2 | B52: =VLOOKUP(A52, COSTS!$I$7:$J$13, 2, FALSE) -> 65 | C52: Lisa | D52: 45971 | E52: 46032 | F52: 097 5266395 | G52: Jemimah | H52: =NOW() -> 46020.438 | I52: =E52-H52 -> 11.562018 | J52: =IF(I52<=0, "EXPIRED", IF(I52<=7, "DUE THIS WEEK", IF(I52<=30, "DUE THIS MONTH", "ACTIVE"))) -> DUE THIS MONTH | K52: NOVEMBER
A53: 4 | B53: =VLOOKUP(A53, COSTS!$I$7:$J$13, 2, FALSE) -> 135 | C53: Cement | D53: 45963 | E53: 46114 | F53: 097 4263564 | G53: Jimbo | H53: =NOW() -> 46020.438 | I53: =E53-H53 -> 93.562018 | J53: =IF(I53<=0, "EXPIRED", IF(I53<=7, "DUE THIS WEEK", IF(I53<=30, "DUE THIS MONTH", "ACTIVE"))) -> ACTIVE | K53: NOVEMBER
A54: 2 | B54: =VLOOKUP(A54, COSTS!$I$7:$J$13, 2, FALSE) -> 65 | C54: Jack | D54: 45962 | E54: 46023 | F54: 097 6548803 | G54: Fridah | H54: =NOW() -> 46020.438 | I54: =E54-H54 -> 2.5620179 | J54: =IF(I54<=0, "EXPIRED", IF(I54<=7, "DUE THIS WEEK", IF(I54<=30, "DUE THIS MONTH", "ACTIVE"))) -> DUE THIS WEEK | K54: NOVEMBER
A55: 6 | B55: =VLOOKUP(A55, COSTS!$I$7:$J$13, 2, FALSE) -> 195 | C55: Tionge | D55: 45962 | E55: 46023 | F55: 765655022 | G55: Londi | H55: =NOW() -> 46020.438 | I55: =E55-H55 -> 2.5620179 | J55: =IF(I55<=0, "EXPIRED", IF(I55<=7, "DUE THIS WEEK", IF(I55<=30, "DUE THIS MONTH", "ACTIVE"))) -> DUE THIS WEEK | K55: NOVEMBER
A56: 5 | B56: =VLOOKUP(A56, COSTS!$B$7:$C$13, 2, FALSE) -> 275 | C56: Kasy | D56: 45960 | E56: 46142 | F56: 772320420 | G56: Mada | H56: =NOW() -> 46020.438 | I56: =E56-H56 -> 121.56202 | J56: =IF(I56<=0, "EXPIRED", IF(I56<=7, "DUE THIS WEEK", IF(I56<=30, "DUE THIS MONTH", "ACTIVE"))) -> ACTIVE | K56: OCTOBER
A57: 1 | B57: =VLOOKUP(A57, COSTS!$B$7:$C$13, 2, FALSE) -> 65 | C57: Chichi | D57: 45958 | E57: 46019 | F57: 760630696 | G57: Chileleko | H57: =NOW() -> 46020.438 | I57: =E57-H57 -> -1.4379821 | J57: =IF(I57<=0, "EXPIRED", IF(I57<=7, "DUE THIS WEEK", IF(I57<=30, "DUE THIS MONTH", "ACTIVE"))) -> EXPIRED | K57: OCTOBER
A58: 1 | B58: =VLOOKUP(A58, COSTS!$B$7:$C$13, 2, FALSE) -> 65 | C58: Liora | D58: 45958 | E58: 46019 | F58: 097 3645518 | G58: Patrick 2 | H58: =NOW() -> 46020.438 | I58: =E58-H58 -> -1.4379821 | J58: =IF(I58<=0, "EXPIRED", IF(I58<=7, "DUE THIS WEEK", IF(I58<=30, "DUE THIS MONTH", "ACTIVE"))) -> EXPIRED | K58: OCTOBER
A59: 5 | B59: =VLOOKUP(A59, COSTS!$B$7:$C$13, 2, FALSE) -> 275 | C59: Kondwani | D59: 45957 | E59: 46108 | F59: 768649316 | G59: Chopper | H59: =NOW() -> 46020.438 | I59: =E59-H59 -> 87.562018 | J59: =IF(I59<=0, "EXPIRED", IF(I59<=7, "DUE THIS WEEK", IF(I59<=30, "DUE THIS MONTH", "ACTIVE"))) -> ACTIVE | K59: OCTOBER
A60: 2 | B60: =VLOOKUP(A60, COSTS!$B$7:$C$13, 2, FALSE) -> 125 | C60: Shammha | D60: 45956 | E60: 46017 | F60: 761351171 | G60: Hellen | H60: =NOW() -> 46020.438 | I60: =E60-H60 -> -3.4379821 | J60: =IF(I60<=0, "EXPIRED", IF(I60<=7, "DUE THIS WEEK", IF(I60<=30, "DUE THIS MONTH", "ACTIVE"))) -> EXPIRED | K60: OCTOBER
A61: 1 | B61: =VLOOKUP(A61, COSTS!$B$7:$C$13, 2, FALSE) -> 65 | D61: 45956 | E61: 46017 | F61: 0 97 4864024 | G61: Tuzange | H61: =NOW() -> 46020.438 | I61: =E61-H61 -> -3.4379821 | J61: =IF(I61<=0, "EXPIRED", IF(I61<=7, "DUE THIS WEEK", IF(I61<=30, "DUE THIS MONTH", "ACTIVE"))) -> EXPIRED | K61: OCTOBER
A62: 2 | B62: =VLOOKUP(A62, COSTS!$B$7:$C$13, 2, FALSE) -> 125 | C62: Shammha | D62: 45956 | E62: 46017 | F62: 097 3039701 | G62: Kassie | H62: =NOW() -> 46020.438 | I62: =E62-H62 -> -3.4379821 | J62: =IF(I62<=0, "EXPIRED", IF(I62<=7, "DUE THIS WEEK", IF(I62<=30, "DUE THIS MONTH", "ACTIVE"))) -> EXPIRED | K62: OCTOBER
A63: 1 | B63: =VLOOKUP(A63, COSTS!$B$7:$C$13, 2, FALSE) -> 65 | C63: 𝐇𝐚𝐤𝐞𝐞𝐦 | D63: 45956 | E63: 46017 | F63: =260776125120 -> 260776125120 | G63: 𝐇𝐚𝐤𝐞𝐞𝐦 | H63: =NOW() -> 46020.438 | I63: =E63-H63 -> -3.4379821 | J63: =IF(I63<=0, "EXPIRED", IF(I63<=7, "DUE THIS WEEK", IF(I63<=30, "DUE THIS MONTH", "ACTIVE"))) -> EXPIRED | K63: OCTOBER
A64: 2 | B64: =VLOOKUP(A64, COSTS!$B$7:$C$13, 2, FALSE) -> 125 | C64: Mukoma Musonda | D64: 45956 | E64: 46017 | F64: 974572669 | G64: Mukoma Musonda | H64: =NOW() -> 46020.438 | I64: =E64-H64 -> -3.4379821 | J64: =IF(I64<=0, "EXPIRED", IF(I64<=7, "DUE THIS WEEK", IF(I64<=30, "DUE THIS MONTH", "ACTIVE"))) -> EXPIRED | K64: OCTOBER
A65: 1 | B65: =VLOOKUP(A65, COSTS!$B$7:$C$13, 2, FALSE) -> 65 | D65: 45955 | E65: 46016 | F65: 760630696 | G65: Chileleko | H65: =NOW() -> 46020.438 | I65: =E65-H65 -> -4.4379821 | J65: =IF(I65<=0, "EXPIRED", IF(I65<=7, "DUE THIS WEEK", IF(I65<=30, "DUE THIS MONTH", "ACTIVE"))) -> EXPIRED | K65: OCTOBER
A66: 2 | B66: =VLOOKUP(A66, COSTS!$B$7:$C$13, 2, FALSE) -> 125 | C66: Bongani Munalula | D66: 45955 | E66: 46016 | F66: 761234732 | G66: Lubuto | H66: =NOW() -> 46020.438 | I66: =E66-H66 -> -4.4379821 | J66: =IF(I66<=0, "EXPIRED", IF(I66<=7, "DUE THIS WEEK", IF(I66<=30, "DUE THIS MONTH", "ACTIVE"))) -> EXPIRED | K66: OCTOBER
D67: 45955 | E67: 46016 | F67: 097 7473902 | G67: Omari | H67: =NOW() -> 46020.438 | I67: =E67-H67 -> -4.4379821 | J67: =IF(I67<=0, "EXPIRED", IF(I67<=7, "DUE THIS WEEK", IF(I67<=30, "DUE THIS MONTH", "ACTIVE"))) -> EXPIRED | K67: OCTOBER
A68: 3 | B68: =VLOOKUP(A68, COSTS!$B$7:$C$13, 2, FALSE) -> 185 | C68: Zharina | D68: 45954 | E68: 46046 | F68: 768460106 | G68: Josh | H68: =NOW() -> 46020.438 | I68: =E68-H68 -> 25.562018 | J68: =IF(I68<=0, "EXPIRED", IF(I68<=7, "DUE THIS WEEK", IF(I68<=30, "DUE THIS MONTH", "ACTIVE"))) -> DUE THIS MONTH | K68: OCTOBER
A69: 2 | B69: =VLOOKUP(A69, COSTS!$B$7:$C$13, 2, FALSE) -> 125 | C69: Vanessa | D69: 45954 | E69: 46015 | F69: 770483704 | G69: Jacobo | H69: =NOW() -> 46020.438 | I69: =E69-H69 -> -5.4379821 | J69: =IF(I69<=0, "EXPIRED", IF(I69<=7, "DUE THIS WEEK", IF(I69<=30, "DUE THIS MONTH", "ACTIVE"))) -> EXPIRED | K69: OCTOBER
A70: 2 | B70: =VLOOKUP(A70, COSTS!$B$7:$C$13, 2, FALSE) -> 125 | D70: 45954 | E70: 46015 | F70: 969291260 | G70: Frankel | H70: =NOW() -> 46020.438 | I70: =E70-H70 -> -5.4379821 | J70: =IF(I70<=0, "EXPIRED", IF(I70<=7, "DUE THIS WEEK", IF(I70<=30, "DUE THIS MONTH", "ACTIVE"))) -> EXPIRED | K70: OCTOBER
A71: 2 | B71: =VLOOKUP(A71, COSTS!$B$7:$C$13, 2, FALSE) -> 125 | C71: Vanessa | D71: 45954 | E71: 46015 | F71: 263 78 021 2566 | G71: Don Darryl | H71: =NOW() -> 46020.438 | I71: =E71-H71 -> -5.4379821 | J71: =IF(I71<=0, "EXPIRED", IF(I71<=7, "DUE THIS WEEK", IF(I71<=30, "DUE THIS MONTH", "ACTIVE"))) -> EXPIRED | K71: OCTOBER
A72: 2 | B72: =VLOOKUP(A72, COSTS!$B$7:$C$13, 2, FALSE) -> 125 | C72: Vanessa | D72: 45954 | E72: 46015 | F72: 0 96 4146591 | G72: Patience Ally | H72: =NOW() -> 46020.438 | I72: =E72-H72 -> -5.4379821 | J72: =IF(I72<=0, "EXPIRED", IF(I72<=7, "DUE THIS WEEK", IF(I72<=30, "DUE THIS MONTH", "ACTIVE"))) -> EXPIRED | K72: OCTOBER
A73: 1 | B73: =VLOOKUP(A73, COSTS!$B$7:$C$13, 2, FALSE) -> 65 | C73: Cement | D73: 45954 | E73: 46015 | F73: 779212100 | G73: Chishala | H73: =NOW() -> 46020.438 | I73: =E73-H73 -> -5.4379821 | J73: =IF(I73<=0, "EXPIRED", IF(I73<=7, "DUE THIS WEEK", IF(I73<=30, "DUE THIS MONTH", "ACTIVE"))) -> EXPIRED | K73: OCTOBER
A74: 2 | B74: =VLOOKUP(A74, COSTS!$B$7:$C$13, 2, FALSE) -> 125 | C74: Kanyanta | D74: 45954 | E74: 46015 | F74: 779692903 | G74: Nate | H74: =NOW() -> 46020.438 | I74: =E74-H74 -> -5.4379821 | J74: =IF(I74<=0, "EXPIRED", IF(I74<=7, "DUE THIS WEEK", IF(I74<=30, "DUE THIS MONTH", "ACTIVE"))) -> EXPIRED | K74: OCTOBER
A75: 2 | B75: =VLOOKUP(A75, COSTS!$B$7:$C$13, 2, FALSE) -> 125 | C75: Zharina | D75: 45954 | E75: 46015 | F75: 60768619582 | G75: Patrick | H75: =NOW() -> 46020.438 | I75: =E75-H75 -> -5.4379821 | J75: =IF(I75<=0, "EXPIRED", IF(I75<=7, "DUE THIS WEEK", IF(I75<=30, "DUE THIS MONTH", "ACTIVE"))) -> EXPIRED | K75: OCTOBER
A76: 2 | B76: =VLOOKUP(A76, COSTS!$B$7:$C$13, 2, FALSE) -> 125 | C76: Vanessa | D76: 45954 | E76: 46015 | F76: 0 96 7150124 | G76: Twavula | H76: =NOW() -> 46020.438 | I76: =E76-H76 -> -5.4379821 | J76: =IF(I76<=0, "EXPIRED", IF(I76<=7, "DUE THIS WEEK", IF(I76<=30, "DUE THIS MONTH", "ACTIVE"))) -> EXPIRED | K76: OCTOBER
A77: 5 | B77: =VLOOKUP(A77, COSTS!$B$7:$C$13, 2, FALSE) -> 275 | C77: Hakeem | D77: 45954 | E77: 46015 | F77: 761365474 | G77: Mwenya 2 | H77: =NOW() -> 46020.438 | I77: =E77-H77 -> -5.4379821 | J77: =IF(I77<=0, "EXPIRED", IF(I77<=7, "DUE THIS WEEK", IF(I77<=30, "DUE THIS MONTH", "ACTIVE"))) -> EXPIRED | K77: OCTOBER
A78: 1 | B78: =VLOOKUP(A78, COSTS!$B$7:$C$13, 2, FALSE) -> 65 | C78: Jack | D78: 45954 | E78: 45985 | F78: 096 6333114 | G78: Precious Maviya. | H78: =NOW() -> 46020.438 | I78: =E78-H78 -> -35.437982 | J78: =IF(I78<=0, "EXPIRED", IF(I78<=7, "DUE THIS WEEK", IF(I78<=30, "DUE THIS MONTH", "ACTIVE"))) -> EXPIRED | K78: OCTOBER
A79: 1 | B79: =VLOOKUP(A79, COSTS!$B$7:$C$13, 2, FALSE) -> 65 | C79: Individual | D79: 45952 | E79: 46013 | F79: 260 97 2947983 | G79: Robyn | H79: =NOW() -> 46020.438 | I79: =E79-H79 -> -7.4379821 | J79: =IF(I79<=0, "EXPIRED", IF(I79<=7, "DUE THIS WEEK", IF(I79<=30, "DUE THIS MONTH", "ACTIVE"))) -> EXPIRED | K79: OCTOBER
A80: 6 | B80: =VLOOKUP(A80, COSTS!$B$7:$C$13, 2, FALSE) -> 325 | C80: Kondwani | D80: 45951 | E80: 46133 | F80: 774683105 | G80: Enjoy | H80: =NOW() -> 46020.438 | I80: =E80-H80 -> 112.56202 | J80: =IF(I80<=0, "EXPIRED", IF(I80<=7, "DUE THIS WEEK", IF(I80<=30, "DUE THIS MONTH", "ACTIVE"))) -> ACTIVE | K80: OCTOBER
A81: 1 | B81: =VLOOKUP(A81, COSTS!$B$7:$C$13, 2, FALSE) -> 65 | C81: Kelis | D81: 45951 | E81: 45982 | F81: 260776943008 | G81: Greg | H81: =NOW() -> 46020.438 | I81: =E81-H81 -> -38.437982 | J81: =IF(I81<=0, "EXPIRED", IF(I81<=7, "DUE THIS WEEK", IF(I81<=30, "DUE THIS MONTH", "ACTIVE"))) -> EXPIRED | K81: OCTOBER
A82: 1 | B82: =VLOOKUP(A82, COSTS!$B$7:$C$13, 2, FALSE) -> 65 | C82: Tionge | D82: 45948 | E82: 46040 | F82: 097 4710399 | G82: Chim | H82: =NOW() -> 46020.438 | I82: =E82-H82 -> 19.562018 | J82: =IF(I82<=0, "EXPIRED", IF(I82<=7, "DUE THIS WEEK", IF(I82<=30, "DUE THIS MONTH", "ACTIVE"))) -> DUE THIS MONTH | K82: OCTOBER
A83: 3 | B83: =VLOOKUP(A83, COSTS!$B$7:$C$13, 2, FALSE) -> 185 | C83: Chimwme | D83: 45947 | E83: 46039 | F83: 260777702700 | G83: TOPFLOORBOS | H83: =NOW() -> 46020.438 | I83: =E83-H83 -> 18.562018 | J83: =IF(I83<=0, "EXPIRED", IF(I83<=7, "DUE THIS WEEK", IF(I83<=30, "DUE THIS MONTH", "ACTIVE"))) -> DUE THIS MONTH | K83: OCTOBER
C84: Tionge | D84: 45947 | E84: 46039 | F84: 0 97 3145230 | G84: Edwin | H84: =NOW() -> 46020.438 | I84: =E84-H84 -> 18.562018 | J84: =IF(I84<=0, "EXPIRED", IF(I84<=7, "DUE THIS WEEK", IF(I84<=30, "DUE THIS MONTH", "ACTIVE"))) -> DUE THIS MONTH | K84: OCTOBER
A85: 6 | B85: =VLOOKUP(A85, COSTS!$B$7:$C$13, 2, FALSE) -> 325 | C85: Sean | D85: 45944 | E85: 46126 | F85: 097 1752609 | G85: Ndabe | H85: =NOW() -> 46020.438 | I85: =E85-H85 -> 105.56202 | J85: =IF(I85<=0, "EXPIRED", IF(I85<=7, "DUE THIS WEEK", IF(I85<=30, "DUE THIS MONTH", "ACTIVE"))) -> ACTIVE | K85: OCTOBER
A86: 6 | B86: =VLOOKUP(A86, COSTS!$B$7:$C$13, 2, FALSE) -> 325 | C86: Andrew | D86: 45944 | E86: 46126 | F86: 777535332 | G86: Luwi | H86: =NOW() -> 46020.438 | I86: =E86-H86 -> 105.56202 | J86: =IF(I86<=0, "EXPIRED", IF(I86<=7, "DUE THIS WEEK", IF(I86<=30, "DUE THIS MONTH", "ACTIVE"))) -> ACTIVE | K86: OCTOBER
A87: 1 | B87: =VLOOKUP(A87, COSTS!$B$7:$C$13, 2, FALSE) -> 65 | C87: Tinashe | D87: 45944 | E87: 46036 | F87: 097 5274087 | G87: Mwenda | H87: =NOW() -> 46020.438 | I87: =E87-H87 -> 15.562018 | J87: =IF(I87<=0, "EXPIRED", IF(I87<=7, "DUE THIS WEEK", IF(I87<=30, "DUE THIS MONTH", "ACTIVE"))) -> DUE THIS MONTH | K87: OCTOBER
A88: 2 | B88: =VLOOKUP(A88, COSTS!$B$7:$C$13, 2, FALSE) -> 125 | C88: Zadok | D88: 45943 | E88: 46004 | F88: 774654611 | G88: Mufaro | H88: =NOW() -> 46020.438 | I88: =E88-H88 -> -16.437982 | J88: =IF(I88<=0, "EXPIRED", IF(I88<=7, "DUE THIS WEEK", IF(I88<=30, "DUE THIS MONTH", "ACTIVE"))) -> EXPIRED | K88: OCTOBER
A89: 3 | B89: =VLOOKUP(A89, COSTS!$B$7:$C$13, 2, FALSE) -> 185 | C89: Lisa | D89: 45941 | E89: 46033 | F89: 096 8748875 | G89: Chabota | H89: =NOW() -> 46020.438 | I89: =E89-H89 -> 12.562018 | J89: =IF(I89<=0, "EXPIRED", IF(I89<=7, "DUE THIS WEEK", IF(I89<=30, "DUE THIS MONTH", "ACTIVE"))) -> DUE THIS MONTH | K89: OCTOBER
A90: 3 | B90: =VLOOKUP(A90, COSTS!$B$7:$C$13, 2, FALSE) -> 185 | C90: Princess | D90: 45940 | E90: 46032 | F90: 260770887128 | G90: Chisenga | H90: =NOW() -> 46020.438 | I90: =E90-H90 -> 11.562018 | J90: =IF(I90<=0, "EXPIRED", IF(I90<=7, "DUE THIS WEEK", IF(I90<=30, "DUE THIS MONTH", "ACTIVE"))) -> DUE THIS MONTH | K90: OCTOBER
A91: 6 | B91: =VLOOKUP(A91, COSTS!$B$7:$C$13, 2, FALSE) -> 325 | C91: Hakeem | D91: 45939 | E91: 46121 | F91: 260776071847 | G91: Knowitall | H91: =NOW() -> 46020.438 | I91: =E91-H91 -> 100.56202 | J91: =IF(I91<=0, "EXPIRED", IF(I91<=7, "DUE THIS WEEK", IF(I91<=30, "DUE THIS MONTH", "ACTIVE"))) -> ACTIVE | K91: OCTOBER
A92: 3 | B92: =VLOOKUP(A92, COSTS!$B$7:$C$13, 2, FALSE) -> 185 | C92: Princess | D92: 45939 | E92: 46031 | F92: 260770887128 | G92: Chisanga | H92: =NOW() -> 46020.438 | I92: =E92-H92 -> 10.562018 | J92: =IF(I92<=0, "EXPIRED", IF(I92<=7, "DUE THIS WEEK", IF(I92<=30, "DUE THIS MONTH", "ACTIVE"))) -> DUE THIS MONTH | K92: OCTOBER
D93: 45939 | E93: 46000 | F93: 243 975 577 009 | G93: Enockbalina | H93: =NOW() -> 46020.438 | I93: =E93-H93 -> -20.437982 | J93: =IF(I93<=0, "EXPIRED", IF(I93<=7, "DUE THIS WEEK", IF(I93<=30, "DUE THIS MONTH", "ACTIVE"))) -> EXPIRED | K93: OCTOBER
A94: 1 | B94: =VLOOKUP(A94, COSTS!$B$7:$C$13, 2, FALSE) -> 65 | C94: Kabaya | D94: 45936 | E94: 45997 | F94: 260 97 8682070 | G94: Patrick | H94: =NOW() -> 46020.438 | I94: =E94-H94 -> -23.437982 | J94: =IF(I94<=0, "EXPIRED", IF(I94<=7, "DUE THIS WEEK", IF(I94<=30, "DUE THIS MONTH", "ACTIVE"))) -> EXPIRED | K94: OCTOBER
A95: 3 | B95: =VLOOKUP(A95, COSTS!$B$7:$C$13, 2, FALSE) -> 185 | C95: Tinashe | D95: 45935 | E95: 46027 | F95: 60 97 1707111 | G95: Cammy | H95: =NOW() -> 46020.438 | I95: =E95-H95 -> 6.5620179 | J95: =IF(I95<=0, "EXPIRED", IF(I95<=7, "DUE THIS WEEK", IF(I95<=30, "DUE THIS MONTH", "ACTIVE"))) -> DUE THIS WEEK | K95: OCTOBER
A96: 2 | B96: =VLOOKUP(A96, COSTS!$B$7:$C$13, 2, FALSE) -> 125 | C96: Jack | D96: 45933 | E96: 47090 | F96: 260 97 7283502 | G96: David stone jr | H96: =NOW() -> 46020.438 | I96: =E96-H96 -> 1069.562 | J96: =IF(I96<=0, "EXPIRED", IF(I96<=7, "DUE THIS WEEK", IF(I96<=30, "DUE THIS MONTH", "ACTIVE"))) -> ACTIVE | K96: OCTOBER
A97: 6 | B97: =VLOOKUP(A97, COSTS!$B$7:$C$13, 2, FALSE) -> 325 | C97: Kelis | D97: 45933 | E97: 46115 | F97: 60767759812 | G97: Ria Myra | H97: =NOW() -> 46020.438 | I97: =E97-H97 -> 94.562018 | J97: =IF(I97<=0, "EXPIRED", IF(I97<=7, "DUE THIS WEEK", IF(I97<=30, "DUE THIS MONTH", "ACTIVE"))) -> ACTIVE | K97: OCTOBER
A98: 3 | B98: =VLOOKUP(A98, COSTS!$B$7:$C$13, 2, FALSE) -> 185 | C98: Chimfwenbe | D98: 45933 | E98: 46025 | F98: 097 6554917 | G98: Nobuhle | H98: =NOW() -> 46020.438 | I98: =E98-H98 -> 4.5620179 | J98: =IF(I98<=0, "EXPIRED", IF(I98<=7, "DUE THIS WEEK", IF(I98<=30, "DUE THIS MONTH", "ACTIVE"))) -> DUE THIS WEEK | K98: OCTOBER
C99: Bongani | D99: 45931 | E99: 46023 | F99: 260570241458 | G99: Bupe | H99: =NOW() -> 46020.438 | I99: =E99-H99 -> 2.5620179 | J99: =IF(I99<=0, "EXPIRED", IF(I99<=7, "DUE THIS WEEK", IF(I99<=30, "DUE THIS MONTH", "ACTIVE"))) -> DUE THIS WEEK | K99: OCTOBER
A100: 1 | B100: =VLOOKUP(A100, COSTS!$B$7:$C$13, 2, FALSE) -> 65 | C100: Wesly | D100: 45927 | E100: 46018 | F100: 260 96 5733144 | G100: Wesly | H100: =NOW() -> 46020.438 | I100: =E100-H100 -> -2.4379821 | J100: =IF(I100<=0, "EXPIRED", IF(I100<=7, "DUE THIS WEEK", IF(I100<=30, "DUE THIS MONTH", "ACTIVE"))) -> EXPIRED | K100: SEPTEMBER
...

Sheet PIVOT Apple Music 2025
A3: Row Labels | B3: Sum of price
A4: FEBRUARY | B4: 620
A5: MARCH | B5: 1290
A6: APRIL | B6: 1715
A7: MAY | B7: 565
A8: JUNE | B8: 435
A9: JULY | B9: 3385
A10: AUGUST | B10: 4520
A11: SEPTEMBER | B11: 4485
A12: OCTOBER | B12: 6150
A13: NOVEMBER | B13: 3687
A14: DECEMBER | B14: 161
A15: (blank) | B15: 125
A16: Grand Total | B16: 27138

Sheet SPOTIFY
A1: Months | B1: price | C1: Family | D1: Paid date | E1: Expire date | F1: Number | G1: Name | H1: TODAYS DATE | I1: DUE DATE | J1: STATUS
A2: 2 | B2: 100 | C2: GREEN yamikophiri50 | D2: 45979 | E2: 46041 | F2: 973302147 | G2: Chichi Chisembele | H2: =NOW() -> 46020.438 | I2: =E2-H2 -> 20.562018 | J2: =IF(I2<=0, "EXPIRED", IF(I2<=7, "DUE THIS WEEK", IF(I2<=30, "DUE THIS MONTH", "ACTIVE"))) -> DUE THIS MONTH
A3: 1 | B3: 75 | C3: GREEN yamikophiri50 | D3: 45973 | E3: 46003 | F3: 972598612 | G3: Njavwa Sichalwe | H3: =NOW() -> 46020.438 | I3: =E3-H3 -> -17.437982 | J3: =IF(I3<=0, "EXPIRED", IF(I3<=7, "DUE THIS WEEK", IF(I3<=30, "DUE THIS MONTH", "ACTIVE"))) -> EXPIRED
A4: 3 | B4: 165 | C4: GREEN yamikophiri50 | D4: 45950 | E4: 46042 | F4: 779039083 | G4: Lusungu Manda Chi | H4: =NOW() -> 46020.438 | I4: =E4-H4 -> 21.562018 | J4: =IF(I4<=0, "EXPIRED", IF(I4<=7, "DUE THIS WEEK", IF(I4<=30, "DUE THIS MONTH", "ACTIVE"))) -> DUE THIS MONTH
A5: 2 | B5: 100 | C5: GREEN yamikophiri50 | D5: 45968 | E5: 46029 | F5: 968027738 | G5: Philimon London | H5: =NOW() -> 46020.438 | I5: =E5-H5 -> 8.5620179 | J5: =IF(I5<=0, "EXPIRED", IF(I5<=7, "DUE THIS WEEK", IF(I5<=30, "DUE THIS MONTH", "ACTIVE"))) -> DUE THIS MONTH
C6: PINK spotifyeasycart | D6: 45673 | G6: Thato | H6: =NOW() -> 46020.438 | I6: =E6-H6 -> -46020.438 | J6: =IF(I6<=0, "EXPIRED", IF(I6<=7, "DUE THIS WEEK", IF(I6<=30, "DUE THIS MONTH", "ACTIVE"))) -> EXPIRED
C7: PINK spotifyeasycart | D7: 46009 | G7: Mu 76 | H7: =NOW() -> 46020.438 | I7: =E7-H7 -> -46020.438 | J7: =IF(I7<=0, "EXPIRED", IF(I7<=7, "DUE THIS WEEK", IF(I7<=30, "DUE THIS MONTH", "ACTIVE"))) -> EXPIRED
C8: PINK spotifyeasycart | H8: =NOW() -> 46020.438 | I8: =E8-H8 -> -46020.438 | J8: =IF(I8<=0, "EXPIRED", IF(I8<=7, "DUE THIS WEEK", IF(I8<=30, "DUE THIS MONTH", "ACTIVE"))) -> EXPIRED
C9: PINK spotifyeasycart | H9: =NOW() -> 46020.438 | I9: =E9-H9 -> -46020.438 | J9: =IF(I9<=0, "EXPIRED", IF(I9<=7, "DUE THIS WEEK", IF(I9<=30, "DUE THIS MONTH", "ACTIVE"))) -> EXPIRED
A10: 3 | B10: 165 | C10: BLUE mwami.jendo | D10: 45940 | E10: 46032 | F10: 977267238 | G10: Katunta Luyando | H10: =NOW() -> 46020.438 | I10: =E10-H10 -> 11.562018 | J10: =IF(I10<=0, "EXPIRED", IF(I10<=7, "DUE THIS WEEK", IF(I10<=30, "DUE THIS MONTH", "ACTIVE"))) -> DUE THIS MONTH
C11: BLUE mwami.jendo | G11: Ngosa Chanda | H11: =NOW() -> 46020.438 | I11: =E11-H11 -> -46020.438 | J11: =IF(I11<=0, "EXPIRED", IF(I11<=7, "DUE THIS WEEK", IF(I11<=30, "DUE THIS MONTH", "ACTIVE"))) -> EXPIRED
A12: 1 | B12: 75 | C12: BLUE mwami.jendo | D12: 45964 | E12: 45994 | F12: 970344497 | G12: Uncle Tinga Chisanga Mutale | H12: =NOW() -> 46020.438 | I12: =E12-H12 -> -26.437982 | J12: =IF(I12<=0, "EXPIRED", IF(I12<=7, "DUE THIS WEEK", IF(I12<=30, "DUE THIS MONTH", "ACTIVE"))) -> EXPIRED
A13: 2 | B13: 100 | C13: BLUE mwami.jendo | D13: 45969 | E13: 45665 | F13: 773956064 | G13: Nicholaus | H13: =NOW() -> 46020.438 | I13: =E13-H13 -> -355.43798 | J13: =IF(I13<=0, "EXPIRED", IF(I13<=7, "DUE THIS WEEK", IF(I13<=30, "DUE THIS MONTH", "ACTIVE"))) -> EXPIRED
A14: 1 | B14: 100 | C14: RED tamika | D14: 45971 | E14: 46001 | F14: 974275830 | G14: Lontua mervin mubanga | H14: =NOW() -> 46020.438 | I14: =E14-H14 -> -19.437982 | J14: =IF(I14<=0, "EXPIRED", IF(I14<=7, "DUE THIS WEEK", IF(I14<=30, "DUE THIS MONTH", "ACTIVE"))) -> EXPIRED
A15: 3 | B15: 165 | C15: RED tamika | D15: 45971 | E15: 46063 | G15: perseverance | H15: =NOW() -> 46020.438 | I15: =E15-H15 -> 42.562018 | J15: =IF(I15<=0, "EXPIRED", IF(I15<=7, "DUE THIS WEEK", IF(I15<=30, "DUE THIS MONTH", "ACTIVE"))) -> ACTIVE
A16: 6 | B16: 205 | C16: RED tamika | D16: 45912 | E16: 46093 | F16: 235998664122 | G16: Hastings | H16: =NOW() -> 46020.438 | I16: =E16-H16 -> 72.562018 | J16: =IF(I16<=0, "EXPIRED", IF(I16<=7, "DUE THIS WEEK", IF(I16<=30, "DUE THIS MONTH", "ACTIVE"))) -> ACTIVE
A17: 3 | B17: 165 | C17: MEROON anittamaxwynn2 | D17: 45937 | E17: 46030 | F17: 978491620 | G17: king muzo | H17: =NOW() -> 46020.438 | I17: =E17-H17 -> 9.5620179 | J17: =IF(I17<=0, "EXPIRED", IF(I17<=7, "DUE THIS WEEK", IF(I17<=30, "DUE THIS MONTH", "ACTIVE"))) -> DUE THIS MONTH
A18: 2 | B18: 100 | C18: MEROON anittamaxwynn2 | D18: 45938 | E18: 45999 | F18: 977946614 | G18: theresa | H18: =NOW() -> 46020.438 | I18: =E18-H18 -> -21.437982 | J18: =IF(I18<=0, "EXPIRED", IF(I18<=7, "DUE THIS WEEK", IF(I18<=30, "DUE THIS MONTH", "ACTIVE"))) -> EXPIRED
C19: MEROON anittamaxwynn2 | G19: kauti cartel | H19: =NOW() -> 46020.438 | I19: =E19-H19 -> -46020.438 | J19: =IF(I19<=0, "EXPIRED", IF(I19<=7, "DUE THIS WEEK", IF(I19<=30, "DUE THIS MONTH", "ACTIVE"))) -> EXPIRED
A20: 2 | B20: 100 | C20: MEROON anittamaxwynn2 | D20: 45940 | E20: 46001 | F20: 779935596 | G20: ayanda moyo | H20: =NOW() -> 46020.438 | I20: =E20-H20 -> -19.437982 | J20: =IF(I20<=0, "EXPIRED", IF(I20<=7, "DUE THIS WEEK", IF(I20<=30, "DUE THIS MONTH", "ACTIVE"))) -> EXPIRED
A21: 2 | B21: 100 | C21: GREY easy cart | D21: 45952 | E21: 46013 | F21: 263712564967 | G21: Alwande Reuben | H21: =NOW() -> 46020.438 | I21: =E21-H21 -> -7.4379821 | J21: =IF(I21<=0, "EXPIRED", IF(I21<=7, "DUE THIS WEEK", IF(I21<=30, "DUE THIS MONTH", "ACTIVE"))) -> EXPIRED
A22: 2 | B22: 100 | C22: GREY easy cart | D22: 45947 | E22: 46008 | G22: Mukenge | H22: =NOW() -> 46020.438 | I22: =E22-H22 -> -12.437982 | J22: =IF(I22<=0, "EXPIRED", IF(I22<=7, "DUE THIS WEEK", IF(I22<=30, "DUE THIS MONTH", "ACTIVE"))) -> EXPIRED
A23: 2 | B23: 100 | C23: GREY easy cart | D23: 45992 | E23: 46055 | G23: Bongani Nsomeka | H23: =NOW() -> 46020.438 | I23: =E23-H23 -> 34.562018 | J23: =IF(I23<=0, "EXPIRED", IF(I23<=7, "DUE THIS WEEK", IF(I23<=30, "DUE THIS MONTH", "ACTIVE"))) -> ACTIVE
G24: Kabwitaloti | H24: =NOW() -> 46020.438 | I24: =E24-H24 -> -46020.438 | J24: =IF(I24<=0, "EXPIRED", IF(I24<=7, "DUE THIS WEEK", IF(I24<=30, "DUE THIS MONTH", "ACTIVE"))) -> EXPIRED

Sheet PRIME VIDEO
A1: Months | B1: price | C1: Paid date | D1: Expire date | E1: Number | F1: Name | G1: TODAYS DATE | H1: DUE DATE | I1: STATUS
A2: 1 | B2: 65 | C2: 45975 | D2: 46005 | E2: 979364673 | F2: Makedah | G2: =TODAY() -> 46020 | H2: =D2-G2 -> -15 | I2: =IF(H2<=0, "EXPIRED", IF(H2<=7, "DUE THIS WEEK", IF(H2<=30, "DUE THIS MONTH", "ACTIVE"))) -> EXPIRED
A3: 12 | B3: 480 | C3: 45975 | D3: 46340 | E3: 972378483 | F3: Ernest Chali | G3: =TODAY() -> 46020 | H3: =D3-G3 -> 320 | I3: =IF(H3<=0, "EXPIRED", IF(H3<=7, "DUE THIS WEEK", IF(H3<=30, "DUE THIS MONTH", "ACTIVE"))) -> ACTIVE
A4: 12 | B4: 480 | C4: 45974 | D4: 46340 | E4: 979983235 | F4: Nathan Mutawali | G4: =TODAY() -> 46020 | H4: =D4-G4 -> 320 | I4: =IF(H4<=0, "EXPIRED", IF(H4<=7, "DUE THIS WEEK", IF(H4<=30, "DUE THIS MONTH", "ACTIVE"))) -> ACTIVE
A5: 1 | B5: 65 | C5: 45975 | D5: 46005 | E5: 60763027788 | F5: Niza | G5: =TODAY() -> 46020 | H5: =D5-G5 -> -15 | I5: =IF(H5<=0, "EXPIRED", IF(H5<=7, "DUE THIS WEEK", IF(H5<=30, "DUE THIS MONTH", "ACTIVE"))) -> EXPIRED
A6: 2 | B6: 105 | C6: 45975 | D6: 46036 | E6: 768544227 | F6: Thema | G6: =TODAY() -> 46020 | H6: =D6-G6 -> 16 | I6: =IF(H6<=0, "EXPIRED", IF(H6<=7, "DUE THIS WEEK", IF(H6<=30, "DUE THIS MONTH", "ACTIVE"))) -> DUE THIS MONTH
A7: 1 | B7: 65 | C7: 45975 | D7: 46005 | E7: 772883599 | F7: Chido | G7: =TODAY() -> 46020 | H7: =D7-G7 -> -15 | I7: =IF(H7<=0, "EXPIRED", IF(H7<=7, "DUE THIS WEEK", IF(H7<=30, "DUE THIS MONTH", "ACTIVE"))) -> EXPIRED
A8: 1 | B8: 65 | C8: 45976 | D8: 46006 | E8: 774967746 | F8: Precious Botha | G8: =TODAY() -> 46020 | H8: =D8-G8 -> -14 | I8: =IF(H8<=0, "EXPIRED", IF(H8<=7, "DUE THIS WEEK", IF(H8<=30, "DUE THIS MONTH", "ACTIVE"))) -> EXPIRED
A9: 1 | B9: 65 | C9: 45977 | D9: 46007 | E9: 777027729 | F9: Chansa sondashi | G9: =TODAY() -> 46020 | H9: =D9-G9 -> -13 | I9: =IF(H9<=0, "EXPIRED", IF(H9<=7, "DUE THIS WEEK", IF(H9<=30, "DUE THIS MONTH", "ACTIVE"))) -> EXPIRED
A10: 2 | B10: 105 | C10: 45985 | D10: 46046 | E10: 970298862 | F10: Mary ngoma | G10: =TODAY() -> 46020 | H10: =D10-G10 -> 26 | I10: =IF(H10<=0, "EXPIRED", IF(H10<=7, "DUE THIS WEEK", IF(H10<=30, "DUE THIS MONTH", "ACTIVE"))) -> DUE THIS MONTH
A11: 2 | B11: 105 | C11: 45990 | D11: 46082 | E11: 571545024 | F11: Adele Toontjies | G11: =TODAY() -> 46020 | H11: =D11-G11 -> 62 | I11: =IF(H11<=0, "EXPIRED", IF(H11<=7, "DUE THIS WEEK", IF(H11<=30, "DUE THIS MONTH", "ACTIVE"))) -> ACTIVE
A12: 2 | B12: 105 | C12: 45991 | D12: 46081 | E12: 968055316 | F12: Elisha Matebele | G12: =TODAY() -> 46020 | H12: =D12-G12 -> 61 | I12: =IF(H12<=0, "EXPIRED", IF(H12<=7, "DUE THIS WEEK", IF(H12<=30, "DUE THIS MONTH", "ACTIVE"))) -> ACTIVE
A13: 1 | B13: 65 | C13: 45997 | D13: 46028 | E13: 960220245 | F13: Larissa Machayi | G13: =TODAY() -> 46020 | H13: =D13-G13 -> 8 | I13: =IF(H13<=0, "EXPIRED", IF(H13<=7, "DUE THIS WEEK", IF(H13<=30, "DUE THIS MONTH", "ACTIVE"))) -> DUE THIS MONTH
C17: PRIME BREAKDOWN | E17: Accounts | F17: COST/AC
C19: 1 month | D19: 65 | E19: 1 | F19: 161
C20: 2 months | D20: 105 | E20: 1 | F20: 161
C21: 3 months | D21: 155 | E21: 1 | F21: 161

Sheet DSTV CUSTOMERS
A1: Months | B1: price | C1: Paid date | D1: Expire date | E1: Number | F1: Name | G1: TODAYS DATE | H1: DUE DATE | I1: STATUS
A2: 1 | B2: 125 | C2: 45960 | D2: 45991 | E2: 973980290 | F2: Loti kawita | G2: =TODAY() -> 46020 | H2: =D2-G2 -> -29 | I2: =IF(H2<=0,"EXPIRED", IF(H2<=7,"DUE THIS WEEK", IF(H2<=30,"DUE THIS MONTH","ACTIVE"))) -> EXPIRED
A3: 1 | B3: 125 | C3: 45956 | D3: 45987 | E3: 973821884 | F3: Sunday | G3: =TODAY() -> 46020 | H3: =D3-G3 -> -33 | I3: =IF(H3<=0,"EXPIRED", IF(H3<=7,"DUE THIS WEEK", IF(H3<=30,"DUE THIS MONTH","ACTIVE"))) -> EXPIRED
A4: 1 | B4: 125 | C4: 45975 | D4: 46005 | E4: 971157371 | F4: Mutale Natasha | G4: =TODAY() -> 46020 | H4: =D4-G4 -> -15 | I4: =IF(H4<=0,"EXPIRED", IF(H4<=7,"DUE THIS WEEK", IF(H4<=30,"DUE THIS MONTH","ACTIVE"))) -> EXPIRED
A5: 1 | B5: 125 | C5: 45975 | D5: 46005 | E5: 977961848 | F5: Stella | G5: =TODAY() -> 46020 | H5: =D5-G5 -> -15 | I5: =IF(H5<=0,"EXPIRED", IF(H5<=7,"DUE THIS WEEK", IF(H5<=30,"DUE THIS MONTH","ACTIVE"))) -> EXPIRED
A6: 3 | B6: 235 | C6: 45980 | D6: 46072 | E6: 975850854 | F6: Esau mwenda | G6: =TODAY() -> 46020 | H6: =D6-G6 -> 52 | I6: =IF(H6<=0,"EXPIRED", IF(H6<=7,"DUE THIS WEEK", IF(H6<=30,"DUE THIS MONTH","ACTIVE"))) -> ACTIVE

Sheet ICLOUD STORAGE 
A1: Months | B1: price | C1: Paid date | D1: Expire date | E1: Number | F1: Name | G1: TODAYS DATE | H1: DUE DATE | I1: STATUS
A2: 1 | B2: 70 | C2: 45871 | D2: 45932 | E2: 760880782 | F2: Lupupa | G2: =TODAY() -> 46020 | H2: =D2-G2 -> -88 | I2: =IF(H2<=0, "EXPIRED", IF(H2<=7, "DUE THIS WEEK", IF(H2<=30, "DUE THIS MONTH", "ACTIVE"))) -> EXPIRED
A3: 2 | B3: 200 | C3: 45881 | D3: 45942 | E3: 978902466 | F3: Mwiche | G3: =TODAY() -> 46020 | H3: =D3-G3 -> -78 | I3: =IF(H3<=0, "EXPIRED", IF(H3<=7, "DUE THIS WEEK", IF(H3<=30, "DUE THIS MONTH", "ACTIVE"))) -> EXPIRED
A4: 1 | B4: 70 | C4: 24/10/2025 | D4: 45985 | E4: 260771944694 | F4: Grace | G4: =TODAY() -> 46020 | H4: =D4-G4 -> -35 | I4: =IF(H4<=0, "EXPIRED", IF(H4<=7, "DUE THIS WEEK", IF(H4<=30, "DUE THIS MONTH", "ACTIVE"))) -> EXPIRED
A5: 1 | B5: 70 | C5: 45954 | D5: 45985 | E5: 974574317 | F5: Tao | G5: =TODAY() -> 46020 | H5: =D5-G5 -> -35 | I5: =IF(H5<=0, "EXPIRED", IF(H5<=7, "DUE THIS WEEK", IF(H5<=30, "DUE THIS MONTH", "ACTIVE"))) -> EXPIRED
A6: 1 | B6: 70 | C6: 45896 | D6: 45927 | E6: 777184558 | F6: Colleen Sinonge | G6: =TODAY() -> 46020 | H6: =D6-G6 -> -93 | I6: =IF(H6<=0, "EXPIRED", IF(H6<=7, "DUE THIS WEEK", IF(H6<=30, "DUE THIS MONTH", "ACTIVE"))) -> EXPIRED
A7: 1 | B7: 70 | C7: 45910 | D7: 45940 | E7: 970839563 | F7: Sky | G7: =TODAY() -> 46020 | H7: =D7-G7 -> -80 | I7: =IF(H7<=0, "EXPIRED", IF(H7<=7, "DUE THIS WEEK", IF(H7<=30, "DUE THIS MONTH", "ACTIVE"))) -> EXPIRED
A8: 1 | B8: 70 | C8: 45910 | D8: 45940 | E8: 973821884 | F8: Sunday | G8: =TODAY() -> 46020 | H8: =D8-G8 -> -80 | I8: =IF(H8<=0, "EXPIRED", IF(H8<=7, "DUE THIS WEEK", IF(H8<=30, "DUE THIS MONTH", "ACTIVE"))) -> EXPIRED
A9: 1 | B9: 70 | C9: 45910 | D9: 45940 | E9: 974562666 | F9: Promise | G9: =TODAY() -> 46020 | H9: =D9-G9 -> -80 | I9: =IF(H9<=0, "EXPIRED", IF(H9<=7, "DUE THIS WEEK", IF(H9<=30, "DUE THIS MONTH", "ACTIVE"))) -> EXPIRED
A10: 1 | B10: 70 | C10: 45910 | D10: 45940 | E10: 260770969579 | F10: Mwiza | G10: =TODAY() -> 46020 | H10: =D10-G10 -> -80 | I10: =IF(H10<=0, "EXPIRED", IF(H10<=7, "DUE THIS WEEK", IF(H10<=30, "DUE THIS MONTH", "ACTIVE"))) -> EXPIRED
A11: 1 | B11: 70 | C11: 45932 | D11: 45963 | E11: 260772734094 | F11: Jackie | G11: =TODAY() -> 46020 | H11: =D11-G11 -> -57 | I11: =IF(H11<=0, "EXPIRED", IF(H11<=7, "DUE THIS WEEK", IF(H11<=30, "DUE THIS MONTH", "ACTIVE"))) -> EXPIRED
A12: 1 | B12: 70 | C12: 45972 | D12: 46002 | E12: 260768937382 | F12: Stephanie | G12: =TODAY() -> 46020 | H12: =D12-G12 -> -18 | I12: =IF(H12<=0, "EXPIRED", IF(H12<=7, "DUE THIS WEEK", IF(H12<=30, "DUE THIS MONTH", "ACTIVE"))) -> EXPIRED
A13: 1 | B13: 70 | C13: 45985 | D13: 46015 | E13: 773740049 | F13: Tiwonge | G13: =TODAY() -> 46020 | H13: =D13-G13 -> -5 | I13: =IF(H13<=0, "EXPIRED", IF(H13<=7, "DUE THIS WEEK", IF(H13<=30, "DUE THIS MONTH", "ACTIVE"))) -> EXPIRED

Sheet NOVEMBER APPLE MUSIC
A1: Months | B1: price | C1: Family | D1: Paid date | E1: Expire date | F1: Number | G1: Name | H1: TODAYS DATE | I1: DUE DATE | J1: STATUS
A2: 1 | B2: =VLOOKUP(A2, COSTS!$I$7:$J$13, 2, FALSE) -> 32 | C2: Stephen | D2: 45990 | E2: 46020 | F2: 964668081 | G2: Gianna mabuku | H2: =NOW() -> 46020.438 | I2: =E2-H2 -> -0.43798206 | J2: =IF(I2<=0,"EXPIRED", IF(I2<=7,"DUE THIS WEEK", IF(H2<=30,"DUE THIS MONTH","ACTIVE"))) -> EXPIRED
A3: 1 | B3: =VLOOKUP(A3, COSTS!$I$7:$J$13, 2, FALSE) -> 32 | C3: Kabaya | D3: 45990 | E3: 46020 | F3: 957985331 | G3: Elizabeth Daka | H3: =NOW() -> 46020.438 | I3: =E3-H3 -> -0.43798206 | J3: =IF(I3<=0, "EXPIRED", IF(I3<=7, "DUE THIS WEEK", IF(I3<=30, "DUE THIS MONTH", "ACTIVE"))) -> EXPIRED
A4: 1 | B4: =VLOOKUP(A4, COSTS!$I$7:$J$13, 2, FALSE) -> 32 | C4: Stephen | D4: 45990 | E4: 46020 | F4: 978490644 | G4: Tapiwa Banda | H4: =NOW() -> 46020.438 | I4: =E4-H4 -> -0.43798206 | J4: =IF(I4<=0, "EXPIRED", IF(I4<=7, "DUE THIS WEEK", IF(I4<=30, "DUE THIS MONTH", "ACTIVE"))) -> EXPIRED
A5: 1 | B5: =VLOOKUP(A5, COSTS!$I$7:$J$13, 2, FALSE) -> 32 | C5: Caleb | D5: 45990 | E5: 46020 | F5: 096 0992424 | G5: Zango m | H5: =NOW() -> 46020.438 | I5: =E5-H5 -> -0.43798206 | J5: =IF(I5<=0, "EXPIRED", IF(I5<=7, "DUE THIS WEEK", IF(I5<=30, "DUE THIS MONTH", "ACTIVE"))) -> EXPIRED
A6: 1 | B6: =VLOOKUP(A6, COSTS!$I$7:$J$13, 2, FALSE) -> 32 | C6: Caleb | D6: 45989 | E6: 46019 | F6: 767070164 | G6: Benjamin lukamba | H6: =NOW() -> 46020.438 | I6: =E6-H6 -> -1.4379821 | J6: =IF(I6<=0, "EXPIRED", IF(I6<=7, "DUE THIS WEEK", IF(I6<=30, "DUE THIS MONTH", "ACTIVE"))) -> EXPIRED
A7: 3 | B7: =VLOOKUP(A7, COSTS!$I$7:$J$13, 2, FALSE) -> 100 | D7: 45989 | E7: 46081 | F7: 978478417 | G7: Paul Katongo | H7: =NOW() -> 46020.438 | I7: =E7-H7 -> 60.562018 | J7: =IF(I7<=0, "EXPIRED", IF(I7<=7, "DUE THIS WEEK", IF(I7<=30, "DUE THIS MONTH", "ACTIVE"))) -> ACTIVE
A8: 3 | B8: =VLOOKUP(A8, COSTS!$I$7:$J$13, 2, FALSE) -> 100 | C8: Kabaya | D8: 45989 | E8: 46081 | F8: 60 97 5467109 | G8: Ameenah Fatacky | H8: =NOW() -> 46020.438 | I8: =E8-H8 -> 60.562018 | J8: =IF(I8<=0, "EXPIRED", IF(I8<=7, "DUE THIS WEEK", IF(I8<=30, "DUE THIS MONTH", "ACTIVE"))) -> ACTIVE
A9: 2 | B9: =VLOOKUP(A9, COSTS!$I$7:$J$13, 2, FALSE) -> 65 | C9: Mukoma | D9: 45989 | E9: 46050 | F9: 097 2159192 | G9: Nelson Malunga | H9: =NOW() -> 46020.438 | I9: =E9-H9 -> 29.562018 | J9: =IF(I9<=0, "EXPIRED", IF(I9<=7, "DUE THIS WEEK", IF(I9<=30, "DUE THIS MONTH", "ACTIVE"))) -> DUE THIS MONTH
A10: 2 | B10: =VLOOKUP(A10, COSTS!$I$7:$J$13, 2, FALSE) -> 65 | D10: 45989 | E10: 46050 | F10: 961817836 | G10: Chiza Ngoma-Nicholas Jr. | H10: =NOW() -> 46020.438 | I10: =E10-H10 -> 29.562018 | J10: =IF(I10<=0, "EXPIRED", IF(I10<=7, "DUE THIS WEEK", IF(I10<=30, "DUE THIS MONTH", "ACTIVE"))) -> DUE THIS MONTH
A11: 12 | B11: =VLOOKUP(A11, COSTS!$I$7:$J$13, 2, FALSE) -> 225 | C11: Wesly | D11: 45988 | E11: 46353 | F11: 973208399 | G11: temwani nawale | H11: =NOW() -> 46020.438 | I11: =E11-H11 -> 332.56202 | J11: =IF(I11<=0, "EXPIRED", IF(I11<=7, "DUE THIS WEEK", IF(I11<=30, "DUE THIS MONTH", "ACTIVE"))) -> ACTIVE
A12: 2 | B12: =VLOOKUP(A12, COSTS!$I$7:$J$13, 2, FALSE) -> 65 | C12: Ziko | D12: 45988 | E12: 46049 | F12: 097 1997704 | G12: Salim | H12: =NOW() -> 46020.438 | I12: =E12-H12 -> 28.562018 | J12: =IF(I12<=0, "EXPIRED", IF(I12<=7, "DUE THIS WEEK", IF(I12<=30, "DUE THIS MONTH", "ACTIVE"))) -> DUE THIS MONTH
A13: 1 | B13: =VLOOKUP(A13, COSTS!$I$7:$J$13, 2, FALSE) -> 32 | C13: Hussan | D13: 45988 | E13: 46018 | F13: 260776149435 | G13: Mukuka Bwalya | H13: =NOW() -> 46020.438 | I13: =E13-H13 -> -2.4379821 | J13: =IF(I13<=0, "EXPIRED", IF(I13<=7, "DUE THIS WEEK", IF(I13<=30, "DUE THIS MONTH", "ACTIVE"))) -> EXPIRED
A14: 1 | B14: =VLOOKUP(A14, COSTS!$I$7:$J$13, 2, FALSE) -> 32 | C14: Wumi | D14: 45987 | E14: 46017 | F14: 960161606 | G14: Erykah Daff | H14: =NOW() -> 46020.438 | I14: =E14-H14 -> -3.4379821 | J14: =IF(I14<=0, "EXPIRED", IF(I14<=7, "DUE THIS WEEK", IF(I14<=30, "DUE THIS MONTH", "ACTIVE"))) -> EXPIRED
A15: 1 | B15: =VLOOKUP(A15, COSTS!$I$7:$J$13, 2, FALSE) -> 32 | C15: Tinashe | D15: 45987 | E15: 46017 | F15: =260770773549 -> 260770773549 | G15: Wana Moonga | H15: =NOW() -> 46020.438 | I15: =E15-H15 -> -3.4379821 | J15: =IF(I15<=0, "EXPIRED", IF(I15<=7, "DUE THIS WEEK", IF(I15<=30, "DUE THIS MONTH", "ACTIVE"))) -> EXPIRED
A16: 2 | B16: =VLOOKUP(A16, COSTS!$I$7:$J$13, 2, FALSE) -> 65 | C16: Wumi | D16: 45986 | E16: 46047 | F16: 972371009 | G16: Twiase | H16: =NOW() -> 46020.438 | I16: =E16-H16 -> 26.562018 | J16: =IF(I16<=0, "EXPIRED", IF(I16<=7, "DUE THIS WEEK", IF(I16<=30, "DUE THIS MONTH", "ACTIVE"))) -> DUE THIS MONTH
A17: 2 | B17: =VLOOKUP(A17, COSTS!$I$7:$J$13, 2, FALSE) -> 65 | C17: Wumi | D17: 45986 | E17: 46047 | F17: 771993800 | G17: Tanaka | H17: =NOW() -> 46020.438 | I17: =E17-H17 -> 26.562018 | J17: =IF(I17<=0, "EXPIRED", IF(I17<=7, "DUE THIS WEEK", IF(I17<=30, "DUE THIS MONTH", "ACTIVE"))) -> DUE THIS MONTH
A18: 2 | B18: =VLOOKUP(A18, COSTS!$I$7:$J$13, 2, FALSE) -> 65 | C18: Zile | D18: 45985 | E18: 46077 | F18: 975741666 | G18: Flo | H18: =NOW() -> 46020.438 | I18: =E18-H18 -> 56.562018 | J18: =IF(I18<=0, "EXPIRED", IF(I18<=7, "DUE THIS WEEK", IF(I18<=30, "DUE THIS MONTH", "ACTIVE"))) -> ACTIVE
A19: 2 | B19: =VLOOKUP(A19, COSTS!$I$7:$J$13, 2, FALSE) -> 65 | C19: Zile | D19: 45985 | E19: 46046 | F19: 097 9758092 | G19: Ethan mvula | H19: =NOW() -> 46020.438 | I19: =E19-H19 -> 25.562018 | J19: =IF(I19<=0, "EXPIRED", IF(I19<=7, "DUE THIS WEEK", IF(I19<=30, "DUE THIS MONTH", "ACTIVE"))) -> DUE THIS MONTH
A20: 2 | B20: =VLOOKUP(A20, COSTS!$I$7:$J$13, 2, FALSE) -> 65 | D20: 45985 | E20: 46046 | F20: 973724846 | G20: Milo Sililo | H20: =NOW() -> 46020.438 | I20: =E20-H20 -> 25.562018 | J20: =IF(I20<=0, "EXPIRED", IF(I20<=7, "DUE THIS WEEK", IF(I20<=30, "DUE THIS MONTH", "ACTIVE"))) -> DUE THIS MONTH
A21: 3 | B21: =VLOOKUP(A21, COSTS!$I$7:$J$13, 2, FALSE) -> 100 | C21: Mwenya | D21: 45984 | E21: 46076 | F21: 776552506 | G21: Latifah | H21: =NOW() -> 46020.438 | I21: =E21-H21 -> 55.562018 | J21: =IF(I21<=0, "EXPIRED", IF(I21<=7, "DUE THIS WEEK", IF(I21<=30, "DUE THIS MONTH", "ACTIVE"))) -> ACTIVE
A22: 2 | B22: =VLOOKUP(A22, COSTS!$I$7:$J$13, 2, FALSE) -> 65 | C22: Namooya | D22: 45984 | E22: 46045 | F22: 954049056 | G22: Jojo | H22: =NOW() -> 46020.438 | I22: =E22-H22 -> 24.562018 | J22: =IF(I22<=0, "EXPIRED", IF(I22<=7, "DUE THIS WEEK", IF(I22<=30, "DUE THIS MONTH", "ACTIVE"))) -> DUE THIS MONTH
A23: 1 | B23: =VLOOKUP(A23, COSTS!$I$7:$J$13, 2, FALSE) -> 32 | C23: Kanyanta | D23: 45984 | E23: 46014 | F23: 097 1833083 | G23: Rafael | H23: =NOW() -> 46020.438 | I23: =E23-H23 -> -6.4379821 | J23: =IF(I23<=0, "EXPIRED", IF(I23<=7, "DUE THIS WEEK", IF(I23<=30, "DUE THIS MONTH", "ACTIVE"))) -> EXPIRED
A24: 3 | B24: =VLOOKUP(A24, COSTS!$I$7:$J$13, 2, FALSE) -> 100 | C24: Warren | D24: 45982 | E24: 46102 | F24: 772734094 | G24: Jackie | H24: =NOW() -> 46020.438 | I24: =E24-H24 -> 81.562018 | J24: =IF(I24<=0, "EXPIRED", IF(I24<=7, "DUE THIS WEEK", IF(I24<=30, "DUE THIS MONTH", "ACTIVE"))) -> ACTIVE
A25: 2 | B25: =VLOOKUP(A25, COSTS!$I$7:$J$13, 2, FALSE) -> 65 | C25: Ziko | D25: 45982 | E25: 46043 | F25: 967990940 | G25: Joy | H25: =NOW() -> 46020.438 | I25: =E25-H25 -> 22.562018 | J25: =IF(I25<=0, "EXPIRED", IF(I25<=7, "DUE THIS WEEK", IF(I25<=30, "DUE THIS MONTH", "ACTIVE"))) -> DUE THIS MONTH
A26: 1 | B26: =VLOOKUP(A26, COSTS!$I$7:$J$13, 2, FALSE) -> 32 | C26: Warren | D26: 45982 | E26: 46012 | F26: 097 1016943 | G26: Jo-Ann | H26: =NOW() -> 46020.438 | I26: =E26-H26 -> -8.4379821 | J26: =IF(I26<=0, "EXPIRED", IF(I26<=7, "DUE THIS WEEK", IF(I26<=30, "DUE THIS MONTH", "ACTIVE"))) -> EXPIRED
A27: 3 | B27: =VLOOKUP(A27, COSTS!$I$7:$J$13, 2, FALSE) -> 100 | C27: Ziko | D27: 45981 | E27: 46073 | F27: 770438283 | G27: Nissa | H27: =NOW() -> 46020.438 | I27: =E27-H27 -> 52.562018 | J27: =IF(I27<=0, "EXPIRED", IF(I27<=7, "DUE THIS WEEK", IF(I27<=30, "DUE THIS MONTH", "ACTIVE"))) -> ACTIVE
A28: 2 | B28: =VLOOKUP(A28, COSTS!$I$7:$J$13, 2, FALSE) -> 65 | C28: Mwitwa | D28: 45978 | E28: 46070 | F28: 0 96 8748589 | G28: Vanessa 2 | H28: =NOW() -> 46020.438 | I28: =E28-H28 -> 49.562018 | J28: =IF(I28<=0, "EXPIRED", IF(I28<=7, "DUE THIS WEEK", IF(I28<=30, "DUE THIS MONTH", "ACTIVE"))) -> ACTIVE
A29: 2 | B29: =VLOOKUP(A29, COSTS!$I$7:$J$13, 2, FALSE) -> 65 | C29: Chipo | D29: 45978 | E29: 46039 | F29: 095 7999876 | G29: Mutibo | H29: =NOW() -> 46020.438 | I29: =E29-H29 -> 18.562018 | J29: =IF(I29<=0, "EXPIRED", IF(I29<=7, "DUE THIS WEEK", IF(I29<=30, "DUE THIS MONTH", "ACTIVE"))) -> DUE THIS MONTH
A30: 1 | B30: =VLOOKUP(A30, COSTS!$I$7:$J$13, 2, FALSE) -> 32 | C30: Agness | D30: 45978 | E30: 46008 | F30: 761673610 | G30: Niza sampa | H30: =NOW() -> 46020.438 | I30: =E30-H30 -> -12.437982 | J30: =IF(I30<=0, "EXPIRED", IF(I30<=7, "DUE THIS WEEK", IF(I30<=30, "DUE THIS MONTH", "ACTIVE"))) -> EXPIRED
A31: 1 | B31: =VLOOKUP(A31, COSTS!$I$7:$J$13, 2, FALSE) -> 32 | C31: Stephan | D31: 45978 | E31: 46008 | F31: 976433541 | G31: Alick Luchembe | H31: =NOW() -> 46020.438 | I31: =E31-H31 -> -12.437982 | J31: =IF(I31<=0, "EXPIRED", IF(I31<=7, "DUE THIS WEEK", IF(I31<=30, "DUE THIS MONTH", "ACTIVE"))) -> EXPIRED
A32: 1 | B32: =VLOOKUP(A32, COSTS!$I$7:$J$13, 2, FALSE) -> 32 | C32: Chipo | D32: 45978 | E32: 46008 | F32: 097 0126202 | G32: Georgina Banda | H32: =NOW() -> 46020.438 | I32: =E32-H32 -> -12.437982 | J32: =IF(I32<=0, "EXPIRED", IF(I32<=7, "DUE THIS WEEK", IF(I32<=30, "DUE THIS MONTH", "ACTIVE"))) -> EXPIRED
A33: 2 | B33: =VLOOKUP(A33, COSTS!$I$7:$J$13, 2, FALSE) -> 65 | C33: Chichi | D33: 45977 | E33: 46038 | F33: 278 874 4694 | G33: Zima | H33: =NOW() -> 46020.438 | I33: =E33-H33 -> 17.562018 | J33: =IF(I33<=0, "EXPIRED", IF(I33<=7, "DUE THIS WEEK", IF(I33<=30, "DUE THIS MONTH", "ACTIVE"))) -> DUE THIS MONTH
A34: 3 | B34: =VLOOKUP(A34, COSTS!$I$7:$J$13, 2, FALSE) -> 100 | C34: Ziko | D34: 45976 | E34: 46068 | F34: 0 97 3809971 | G34: Chikondi | H34: =NOW() -> 46020.438 | I34: =E34-H34 -> 47.562018 | J34: =IF(I34<=0, "EXPIRED", IF(I34<=7, "DUE THIS WEEK", IF(I34<=30, "DUE THIS MONTH", "ACTIVE"))) -> ACTIVE
A35: 2 | B35: =VLOOKUP(A35, COSTS!$I$7:$J$13, 2, FALSE) -> 65 | C35: Hassan | D35: 45976 | E35: 46037 | F35: 773740049 | G35: Tiwonge | H35: =NOW() -> 46020.438 | I35: =E35-H35 -> 16.562018 | J35: =IF(I35<=0, "EXPIRED", IF(I35<=7, "DUE THIS WEEK", IF(I35<=30, "DUE THIS MONTH", "ACTIVE"))) -> DUE THIS MONTH
A36: 2 | B36: =VLOOKUP(A36, COSTS!$I$7:$J$13, 2, FALSE) -> 65 | C36: Chipo | D36: 45976 | E36: 46037 | F36: 097 0633260 | G36: Kassie 2 | H36: =NOW() -> 46020.438 | I36: =E36-H36 -> 16.562018 | J36: =IF(I36<=0, "EXPIRED", IF(I36<=7, "DUE THIS WEEK", IF(I36<=30, "DUE THIS MONTH", "ACTIVE"))) -> DUE THIS MONTH
A37: 1 | B37: =VLOOKUP(A37, COSTS!$I$7:$J$13, 2, FALSE) -> 32 | C37: Princess | D37: 45976 | E37: 46006 | F37: 772691176 | G37: Michelle | H37: =NOW() -> 46020.438 | I37: =E37-H37 -> -14.437982 | J37: =IF(I37<=0, "EXPIRED", IF(I37<=7, "DUE THIS WEEK", IF(I37<=30, "DUE THIS MONTH", "ACTIVE"))) -> EXPIRED
A38: 1 | B38: =VLOOKUP(A38, COSTS!$I$7:$J$13, 2, FALSE) -> 32 | C38: Chichi | D38: 45976 | E38: 46006 | F38: 263 78 874 4694 | G38: Yamihle | H38: =NOW() -> 46020.438 | I38: =E38-H38 -> -14.437982 | J38: =IF(I38<=0, "EXPIRED", IF(I38<=7, "DUE THIS WEEK", IF(I38<=30, "DUE THIS MONTH", "ACTIVE"))) -> EXPIRED
A39: 6 | B39: =VLOOKUP(A39, COSTS!$I$7:$J$13, 2, FALSE) -> 195 | C39: Mwenya | D39: 45975 | E39: 46067 | F39: 60779320678 | G39: David sampa | H39: =NOW() -> 46020.438 | I39: =E39-H39 -> 46.562018 | J39: =IF(I39<=0, "EXPIRED", IF(I39<=7, "DUE THIS WEEK", IF(I39<=30, "DUE THIS MONTH", "ACTIVE"))) -> ACTIVE
A40: 2 | B40: =VLOOKUP(A40, COSTS!$I$7:$J$13, 2, FALSE) -> 65 | C40: Tionge | D40: 45975 | E40: 46036 | F40: 097 0702121 | G40: Thwani | H40: =NOW() -> 46020.438 | I40: =E40-H40 -> 15.562018 | J40: =IF(I40<=0, "EXPIRED", IF(I40<=7, "DUE THIS WEEK", IF(I40<=30, "DUE THIS MONTH", "ACTIVE"))) -> DUE THIS MONTH
A41: 1 | B41: =VLOOKUP(A41, COSTS!$I$7:$J$13, 2, FALSE) -> 32 | D41: 45975 | E41: 46005 | F41: 097 5367166 | G41: Tehillah | H41: =NOW() -> 46020.438 | I41: =E41-H41 -> -15.437982 | J41: =IF(I41<=0, "EXPIRED", IF(I41<=7, "DUE THIS WEEK", IF(I41<=30, "DUE THIS MONTH", "ACTIVE"))) -> EXPIRED
A42: 3 | B42: =VLOOKUP(A42, COSTS!$I$7:$J$13, 2, FALSE) -> 100 | C42: Panji | D42: 45974 | E42: 46035 | F42: 774967746 | G42: MB | H42: =NOW() -> 46020.438 | I42: =E42-H42 -> 14.562018 | J42: =IF(I42<=0, "EXPIRED", IF(I42<=7, "DUE THIS WEEK", IF(I42<=30, "DUE THIS MONTH", "ACTIVE"))) -> DUE THIS MONTH
A43: 12 | B43: =VLOOKUP(A43, COSTS!$I$7:$J$13, 2, FALSE) -> 225 | C43: Panji | D43: 45973 | E43: 46368 | F43: 768846867 | G43: Mwenya 3 | H43: =NOW() -> 46020.438 | I43: =E43-H43 -> 347.56202 | J43: =IF(I43<=0, "EXPIRED", IF(I43<=7, "DUE THIS WEEK", IF(I43<=30, "DUE THIS MONTH", "ACTIVE"))) -> ACTIVE
A44: 3 | B44: =VLOOKUP(A44, COSTS!$I$7:$J$13, 2, FALSE) -> 100 | C44: Panji | D44: 45973 | E44: 46065 | F44: 096 7101367 | G44: Chikondi | H44: =NOW() -> 46020.438 | I44: =E44-H44 -> 44.562018 | J44: =IF(I44<=0, "EXPIRED", IF(I44<=7, "DUE THIS WEEK", IF(I44<=30, "DUE THIS MONTH", "ACTIVE"))) -> ACTIVE
A45: 3 | B45: =VLOOKUP(A45, COSTS!$I$7:$J$13, 2, FALSE) -> 100 | C45: Panji | D45: 45973 | E45: 46065 | F45: 776624932 | G45: Clarence | H45: =NOW() -> 46020.438 | I45: =E45-H45 -> 44.562018 | J45: =IF(I45<=0, "EXPIRED", IF(I45<=7, "DUE THIS WEEK", IF(I45<=30, "DUE THIS MONTH", "ACTIVE"))) -> ACTIVE
A46: 2 | B46: =VLOOKUP(A46, COSTS!$I$7:$J$13, 2, FALSE) -> 65 | C46: 𝐇𝐚𝐤𝐞𝐞𝐦 | D46: 45972 | E46: 46033 | F46: 966944143 | G46: Zoe | H46: =NOW() -> 46020.438 | I46: =E46-H46 -> 12.562018 | J46: =IF(I46<=0, "EXPIRED", IF(I46<=7, "DUE THIS WEEK", IF(I46<=30, "DUE THIS MONTH", "ACTIVE"))) -> DUE THIS MONTH
A47: 2 | B47: =VLOOKUP(A47, COSTS!$I$7:$J$13, 2, FALSE) -> 65 | C47: Wendy | D47: 45972 | E47: 46033 | F47: 773953416 | G47: Tyann | H47: =NOW() -> 46020.438 | I47: =E47-H47 -> 12.562018 | J47: =IF(I47<=0, "EXPIRED", IF(I47<=7, "DUE THIS WEEK", IF(I47<=30, "DUE THIS MONTH", "ACTIVE"))) -> DUE THIS MONTH
A48: 2 | B48: =VLOOKUP(A48, COSTS!$I$7:$J$13, 2, FALSE) -> 65 | C48: Lisa | D48: 45971 | E48: 46032 | F48: 097 5266395 | G48: Jemimah | H48: =NOW() -> 46020.438 | I48: =E48-H48 -> 11.562018 | J48: =IF(I48<=0, "EXPIRED", IF(I48<=7, "DUE THIS WEEK", IF(I48<=30, "DUE THIS MONTH", "ACTIVE"))) -> DUE THIS MONTH
A49: 4 | B49: =VLOOKUP(A49, COSTS!$I$7:$J$13, 2, FALSE) -> 135 | C49: Cement | D49: 45963 | E49: 46114 | F49: 097 4263564 | G49: Jimbo | H49: =NOW() -> 46020.438 | I49: =E49-H49 -> 93.562018 | J49: =IF(I49<=0, "EXPIRED", IF(I49<=7, "DUE THIS WEEK", IF(I49<=30, "DUE THIS MONTH", "ACTIVE"))) -> ACTIVE
A50: 2 | B50: =VLOOKUP(A50, COSTS!$I$7:$J$13, 2, FALSE) -> 65 | C50: Jack | D50: 45962 | E50: 46023 | F50: 097 6548803 | G50: Fridah | H50: =NOW() -> 46020.438 | I50: =E50-H50 -> 2.5620179 | J50: =IF(I50<=0, "EXPIRED", IF(I50<=7, "DUE THIS WEEK", IF(I50<=30, "DUE THIS MONTH", "ACTIVE"))) -> DUE THIS WEEK
A51: 6 | B51: =VLOOKUP(A51, COSTS!$I$7:$J$13, 2, FALSE) -> 195 | C51: Tionge | D51: 45962 | E51: 46023 | F51: 765655022 | G51: Londi | H51: =NOW() -> 46020.438 | I51: =E51-H51 -> 2.5620179 | J51: =IF(I51<=0, "EXPIRED", IF(I51<=7, "DUE THIS WEEK", IF(I51<=30, "DUE THIS MONTH", "ACTIVE"))) -> DUE THIS WEEK

Sheet NOVEMBER APPLE MUSIC EXPENSES
A1: ORDER ACCOUNT | B1: PAYMENT | C1: DATE
A2: Apple Music balance | B2: 67 | C2: 45989 | E2: APPLE MUSIC
A3: Apple Music fam | B3: 67 | C3: 45973 | E3: ACOOUNTS BOUGHT | F3: INDIVIDUAL ACCOUNTS | G3: HOW MANY WHERE FILLED? | H3: ONE YEAR CUSTOMER | I3: MONTHLY
A4: Apple Music fam | B4: 67 | C4: 45974 | E4: 15 | F4: =15*5 -> 75 | G4: 50 | H4: 2 | I4: =SUM(B2:B16) -> 1005
A5: Apple Music fam | B5: 67 | C5: 45975
A6: Apple Music fam | B6: 67 | C6: 45975 | E6: CRUNCHYROLL
A7: Apple Music fam | B7: 67 | C7: 45976 | E7: ACOOUNTS BOUGHT | F7: INDIVIDUAL ACCOUNTS | G7: HOW MANY WHERE FILLED? | H7: ONE YEAR CUSTOMER | I7: MONTHLY
A8: Apple Music fam | B8: 67 | C8: 45980 | E8: 2 | F8: =E8*5 -> 10 | G8: 50 | H8: 2 | I8: 70
A9: Apple Music fam | B9: 67 | C9: 45982
A10: Apple Music fam | B10: 67 | C10: 45985 | E10: NETFLIX
A11: Apple Music fam | B11: 67 | C11: 45985 | E11: ACOOUNTS BOUGHT | F11: INDIVIDUAL ACCOUNTS | G11: HOW MANY WHERE FILLED? | H11: ONE YEAR CUSTOMER | I11: MONTHLY
A12: Apple Music fam | B12: 67 | C12: 45988 | E12: 3 | F12: =E12*5 -> 15 | G12: 50 | H12: 2 | I12: =SUM(B22:B24) -> 634
A13: Apple Music fam | B13: 67 | C13: 45988
A14: Apple Music fam | B14: 67 | C14: 45990 | E14: SPOTIFY
A15: Apple Music fam | B15: 67 | C15: 45975 | E15: ACOOUNTS BOUGHT | F15: INDIVIDUAL ACCOUNTS | G15: HOW MANY WHERE FILLED? | H15: ONE YEAR CUSTOMER | I15: MONTHLY
A16: Apple Music fam | B16: 67 | C16: 45976 | E16: 3 | F16: =E16*5 -> 15 | G16: 7 | H16: 2 | I16: =SUM(B26:B28) -> 347
A17: Crunchy roll | B17: 35 | C17: 45991
A18: Crunchy roll | B18: 35 | C18: 45991
A19: Disney plus | B19: 225 | C19: 45977
A20: HBO | B20: 100 | C20: 45988
A21: Individual apple | B21: 35 | C21: 45991
A22: Netflix | B22: 189 | C22: 45975
A23: Netflix | B23: 260 | C23: 45986
A24: Netflix | B24: 185 | C24: 45991
A25: prime | B25: 161 | C25: 45988
A26: Spotify | B26: 67 | C26: 45974
A27: Spotify | B27: 140 | C27: 45988
A28: Spotify | B28: 140 | C28: 45988
A29: TOTAL FOR NOVEMBER | B29: =SUM(B2:B28) -> 2577

Sheet 2024 & BAD RECORDS
A1: Months | B1: price | C1: Family | D1: Paid date | E1: Expire date | F1: Number | G1: Name | H1: TODAYS DATE | I1: DUE DATE | J1: STATUS
A2: 1 | B2: =VLOOKUP(A2, COSTS!$B$7:$C$13, 2, FALSE) -> 65 | C2: Ray | D2: 45485 | E2: 45942 | F2: 964533244 | G2: Mulenga | H2: =NOW() -> 46020.438 | I2: =E2-H2 -> -78.437982 | J2: =IF(I2<=0, "EXPIRED", IF(I2<=7, "DUE THIS WEEK", IF(I2<=30, "DUE THIS MONTH", "ACTIVE"))) -> EXPIRED
A3: 6 | B3: =VLOOKUP(A3, COSTS!$B$7:$C$13, 2, FALSE) -> 325 | C3: Ziko | D3: 45371 | E3: 46011 | F3: 971792821 | G3: Kauti | H3: =NOW() -> 46020.438 | I3: =E3-H3 -> -9.4379821 | J3: =IF(I3<=0, "EXPIRED", IF(I3<=7, "DUE THIS WEEK", IF(I3<=30, "DUE THIS MONTH", "ACTIVE"))) -> EXPIRED
E4: 29/ | F4: 975191398 | G4: Ali Mohammad | H4: =NOW() -> 46020.438 | J4: =IF(I4<=0, "EXPIRED", IF(I4<=7, "DUE THIS WEEK", IF(I4<=30, "DUE THIS MONTH", "ACTIVE"))) -> EXPIRED
E5: 46068 | F5: 773740049 | G5: Tiwonge | H5: =NOW() -> 46020.438 | J5: =IF(I5<=0, "EXPIRED", IF(I5<=7, "DUE THIS WEEK", IF(I5<=30, "DUE THIS MONTH", "ACTIVE"))) -> EXPIRED
F6: 779384200 | G6: Dylan | H6: =NOW() -> 46020.438 | I6: =E6-H6 -> -46020.438 | J6: =IF(I6<=0, "EXPIRED", IF(I6<=7, "DUE THIS WEEK", IF(I6<=30, "DUE THIS MONTH", "ACTIVE"))) -> EXPIRED
A7: 1 | B7: =VLOOKUP(A7, COSTS!$B$7:$C$13, 2, FALSE) -> 65 | C7: Mwitwa | G7: Elyse Mpawenayo | H7: =NOW() -> 46020.438 | I7: =E7-H7 -> -46020.438 | J7: =IF(I7<=0, "EXPIRED", IF(I7<=7, "DUE THIS WEEK", IF(I7<=30, "DUE THIS MONTH", "ACTIVE"))) -> EXPIRED
C8: Kondwani | F8: 260776549416 | G8: Kondwani | H8: =NOW() -> 46020.438 | I8: =E8-H8 -> -46020.438 | J8: =IF(I8<=0, "EXPIRED", IF(I8<=7, "DUE THIS WEEK", IF(I8<=30, "DUE THIS MONTH", "ACTIVE"))) -> EXPIRED
F9: 975726804 | G9: Lethiwe Lukumba | H9: =NOW() -> 46020.438 | I9: =E9-H9 -> -46020.438 | J9: =IF(I9<=0, "EXPIRED", IF(I9<=7, "DUE THIS WEEK", IF(I9<=30, "DUE THIS MONTH", "ACTIVE"))) -> EXPIRED
A10: 2 | B10: =VLOOKUP(A10, COSTS!$B$7:$C$13, 2, FALSE) -> 125 | C10: Wendy kalinda | F10: 097 4574317 | G10: Tao | H10: =NOW() -> 46020.438 | I10: =E10-H10 -> -46020.438 | J10: =IF(I10<=0, "EXPIRED", IF(I10<=7, "DUE THIS WEEK", IF(I10<=30, "DUE THIS MONTH", "ACTIVE"))) -> EXPIRED
